{
 "j2cli.__author__":{
  "__set__":true,
  "elements":[
   "j2cli-0.3.10-py_0"
  ]
 },
 "j2cli.__email__":{
  "__set__":true,
  "elements":[
   "j2cli-0.3.10-py_0"
  ]
 },
 "j2cli.__version__":{
  "__set__":true,
  "elements":[
   "j2cli-0.3.10-py_0"
  ]
 },
 "j2cli.cli":{
  "__set__":true,
  "elements":[
   "j2cli-0.3.10-py_0"
  ]
 },
 "j2cli.cli.FilePathLoader":{
  "__set__":true,
  "elements":[
   "j2cli-0.3.10-py_0"
  ]
 },
 "j2cli.cli.Jinja2TemplateRenderer":{
  "__set__":true,
  "elements":[
   "j2cli-0.3.10-py_0"
  ]
 },
 "j2cli.cli.main":{
  "__set__":true,
  "elements":[
   "j2cli-0.3.10-py_0"
  ]
 },
 "j2cli.cli.render_command":{
  "__set__":true,
  "elements":[
   "j2cli-0.3.10-py_0"
  ]
 },
 "j2cli.context":{
  "__set__":true,
  "elements":[
   "j2cli-0.3.10-py_0"
  ]
 },
 "j2cli.context.FORMATS":{
  "__set__":true,
  "elements":[
   "j2cli-0.3.10-py_0"
  ]
 },
 "j2cli.context._parse_env":{
  "__set__":true,
  "elements":[
   "j2cli-0.3.10-py_0"
  ]
 },
 "j2cli.context._parse_ini":{
  "__set__":true,
  "elements":[
   "j2cli-0.3.10-py_0"
  ]
 },
 "j2cli.context._parse_json":{
  "__set__":true,
  "elements":[
   "j2cli-0.3.10-py_0"
  ]
 },
 "j2cli.context._parse_yaml":{
  "__set__":true,
  "elements":[
   "j2cli-0.3.10-py_0"
  ]
 },
 "j2cli.context.basestring":{
  "__set__":true,
  "elements":[
   "j2cli-0.3.10-py_0"
  ]
 },
 "j2cli.context.read_context_data":{
  "__set__":true,
  "elements":[
   "j2cli-0.3.10-py_0"
  ]
 },
 "j2cli.extras":{
  "__set__":true,
  "elements":[
   "j2cli-0.3.10-py_0"
  ]
 },
 "j2cli.extras.customize":{
  "__set__":true,
  "elements":[
   "j2cli-0.3.10-py_0"
  ]
 },
 "j2cli.extras.customize.CustomizationModule":{
  "__set__":true,
  "elements":[
   "j2cli-0.3.10-py_0"
  ]
 },
 "j2cli.extras.filters":{
  "__set__":true,
  "elements":[
   "j2cli-0.3.10-py_0"
  ]
 },
 "j2cli.extras.filters.docker_link":{
  "__set__":true,
  "elements":[
   "j2cli-0.3.10-py_0"
  ]
 },
 "j2cli.extras.filters.env":{
  "__set__":true,
  "elements":[
   "j2cli-0.3.10-py_0"
  ]
 },
 "j2cli.main":{
  "__set__":true,
  "elements":[
   "j2cli-0.3.10-py_0"
  ]
 }
}