{
 "LDAStools.LDASlogging._LDASlogging":{
  "__set__":true,
  "elements":[
   "python-ldas-tools-ldasgen-2.6.7-py38ha0d09dd_1"
  ]
 },
 "LDAStools.LDASlogging._swig_getattr":{
  "__set__":true,
  "elements":[
   "python-ldas-tools-ldasgen-2.6.7-py38ha0d09dd_1"
  ]
 },
 "LDAStools.LDASlogging._swig_property":{
  "__set__":true,
  "elements":[
   "python-ldas-tools-ldasgen-2.6.7-py38ha0d09dd_1"
  ]
 },
 "LDAStools.LDASlogging._swig_repr":{
  "__set__":true,
  "elements":[
   "python-ldas-tools-ldasgen-2.6.7-py38ha0d09dd_1"
  ]
 },
 "LDAStools.LDASlogging._swig_setattr":{
  "__set__":true,
  "elements":[
   "python-ldas-tools-ldasgen-2.6.7-py38ha0d09dd_1"
  ]
 },
 "LDAStools.LDASlogging.new_instancemethod":{
  "__set__":true,
  "elements":[
   "python-ldas-tools-ldasgen-2.6.7-py38ha0d09dd_1"
  ]
 },
 "LDAStools.diskCache.BUILD__SWIG__LDAS_PYTHON_I":{
  "__set__":true,
  "elements":[
   "python-ldas-tools-diskcacheapi-2.6.8-py27hc9558a2_0"
  ]
 },
 "LDAStools.diskCache.LDAS_DOC_PROTO_WITHOUT_TYPES":{
  "__set__":true,
  "elements":[
   "python-ldas-tools-diskcacheapi-2.6.8-py27hc9558a2_0"
  ]
 },
 "LDAStools.diskCache.LDAS_DOC_PROTO_WITH_TYPES":{
  "__set__":true,
  "elements":[
   "python-ldas-tools-diskcacheapi-2.6.8-py27hc9558a2_0"
  ]
 },
 "LDAStools.diskCache._diskCache":{
  "__set__":true,
  "elements":[
   "python-ldas-tools-diskcacheapi-2.6.8-py27hc9558a2_0"
  ]
 },
 "LDAStools.diskCache._swig_getattr":{
  "__set__":true,
  "elements":[
   "python-ldas-tools-diskcacheapi-2.6.8-py27hc9558a2_0"
  ]
 },
 "LDAStools.diskCache._swig_property":{
  "__set__":true,
  "elements":[
   "python-ldas-tools-diskcacheapi-2.6.8-py27hc9558a2_0"
  ]
 },
 "LDAStools.diskCache._swig_repr":{
  "__set__":true,
  "elements":[
   "python-ldas-tools-diskcacheapi-2.6.8-py27hc9558a2_0"
  ]
 },
 "LDAStools.diskCache._swig_setattr":{
  "__set__":true,
  "elements":[
   "python-ldas-tools-diskcacheapi-2.6.8-py27hc9558a2_0"
  ]
 },
 "LDAStools.diskCache.new_instancemethod":{
  "__set__":true,
  "elements":[
   "python-ldas-tools-diskcacheapi-2.6.8-py27hc9558a2_0"
  ]
 }
}