{
 "vega.Vega":{
  "__set__":true,
  "elements":[
   "vega-2.3.2-py36_0",
   "vega-2.6.0-py37_0"
  ]
 },
 "vega.__all__":{
  "__set__":true,
  "elements":[
   "vega-2.3.2-py36_0",
   "vega-2.6.0-py37_0"
  ]
 },
 "vega.__version__":{
  "__set__":true,
  "elements":[
   "vega-2.3.2-py36_0",
   "vega-2.6.0-py37_0"
  ]
 },
 "vega._jupyter_nbextension_paths":{
  "__set__":true,
  "elements":[
   "vega-2.3.2-py36_0",
   "vega-2.6.0-py37_0"
  ]
 },
 "vega.base":{
  "__set__":true,
  "elements":[
   "vega-2.3.2-py36_0",
   "vega-2.6.0-py37_0"
  ]
 },
 "vega.base.VegaBase":{
  "__set__":true,
  "elements":[
   "vega-2.3.2-py36_0",
   "vega-2.6.0-py37_0"
  ]
 },
 "vega.find_static_assets":{
  "__set__":true,
  "elements":[
   "vega-2.3.2-py36_0",
   "vega-2.6.0-py37_0"
  ]
 },
 "vega.tests":{
  "__set__":true,
  "elements":[
   "vega-2.3.2-py36_0",
   "vega-2.6.0-py37_0"
  ]
 },
 "vega.tests.test_outputs":{
  "__set__":true,
  "elements":[
   "vega-2.3.2-py36_0",
   "vega-2.6.0-py37_0"
  ]
 },
 "vega.tests.test_outputs.JSON_DATA":{
  "__set__":true,
  "elements":[
   "vega-2.3.2-py36_0",
   "vega-2.6.0-py37_0"
  ]
 },
 "vega.tests.test_outputs.PANDAS_DATA":{
  "__set__":true,
  "elements":[
   "vega-2.3.2-py36_0",
   "vega-2.6.0-py37_0"
  ]
 },
 "vega.tests.test_outputs.VEGALITE_SPEC":{
  "__set__":true,
  "elements":[
   "vega-2.3.2-py36_0",
   "vega-2.6.0-py37_0"
  ]
 },
 "vega.tests.test_outputs.VEGA_SPEC":{
  "__set__":true,
  "elements":[
   "vega-2.3.2-py36_0",
   "vega-2.6.0-py37_0"
  ]
 },
 "vega.tests.test_outputs.test_vega_output":{
  "__set__":true,
  "elements":[
   "vega-2.3.2-py36_0",
   "vega-2.6.0-py37_0"
  ]
 },
 "vega.tests.test_outputs.test_vegalite_output":{
  "__set__":true,
  "elements":[
   "vega-2.3.2-py36_0",
   "vega-2.6.0-py37_0"
  ]
 },
 "vega.tests.test_utils":{
  "__set__":true,
  "elements":[
   "vega-2.3.2-py36_0",
   "vega-2.6.0-py37_0"
  ]
 },
 "vega.tests.test_utils.JSON_DATA":{
  "__set__":true,
  "elements":[
   "vega-2.3.2-py36_0",
   "vega-2.6.0-py37_0"
  ]
 },
 "vega.tests.test_utils.PANDAS_DATA":{
  "__set__":true,
  "elements":[
   "vega-2.3.2-py36_0",
   "vega-2.6.0-py37_0"
  ]
 },
 "vega.tests.test_utils.VEGALITE_SPEC":{
  "__set__":true,
  "elements":[
   "vega-2.3.2-py36_0",
   "vega-2.6.0-py37_0"
  ]
 },
 "vega.tests.test_utils.test_prepare_spec":{
  "__set__":true,
  "elements":[
   "vega-2.3.2-py36_0",
   "vega-2.6.0-py37_0"
  ]
 },
 "vega.tests.test_utils.test_sanitize_dataframe":{
  "__set__":true,
  "elements":[
   "vega-2.3.2-py36_0",
   "vega-2.6.0-py37_0"
  ]
 },
 "vega.utils":{
  "__set__":true,
  "elements":[
   "vega-2.3.2-py36_0",
   "vega-2.6.0-py37_0"
  ]
 },
 "vega.utils.abs_path":{
  "__set__":true,
  "elements":[
   "vega-2.3.2-py36_0",
   "vega-2.6.0-py37_0"
  ]
 },
 "vega.utils.escape":{
  "__set__":true,
  "elements":[
   "vega-2.3.2-py36_0",
   "vega-2.6.0-py37_0"
  ]
 },
 "vega.utils.get_content":{
  "__set__":true,
  "elements":[
   "vega-2.3.2-py36_0",
   "vega-2.6.0-py37_0"
  ]
 },
 "vega.utils.prepare_spec":{
  "__set__":true,
  "elements":[
   "vega-2.3.2-py36_0",
   "vega-2.6.0-py37_0"
  ]
 },
 "vega.utils.sanitize_dataframe":{
  "__set__":true,
  "elements":[
   "vega-2.3.2-py36_0",
   "vega-2.6.0-py37_0"
  ]
 },
 "vega.vega":{
  "__set__":true,
  "elements":[
   "vega-2.3.2-py36_0",
   "vega-2.6.0-py37_0"
  ]
 },
 "vega.vega.Vega":{
  "__set__":true,
  "elements":[
   "vega-2.3.2-py36_0",
   "vega-2.6.0-py37_0"
  ]
 },
 "vega.vega.__all__":{
  "__set__":true,
  "elements":[
   "vega-2.3.2-py36_0",
   "vega-2.6.0-py37_0"
  ]
 },
 "vega.vega.entry_point_renderer":{
  "__set__":true,
  "elements":[
   "vega-2.3.2-py36_0",
   "vega-2.6.0-py37_0"
  ]
 },
 "vega.vegalite":{
  "__set__":true,
  "elements":[
   "vega-2.3.2-py36_0",
   "vega-2.6.0-py37_0"
  ]
 },
 "vega.vegalite.VegaLite":{
  "__set__":true,
  "elements":[
   "vega-2.3.2-py36_0",
   "vega-2.6.0-py37_0"
  ]
 },
 "vega.vegalite.__all__":{
  "__set__":true,
  "elements":[
   "vega-2.3.2-py36_0",
   "vega-2.6.0-py37_0"
  ]
 },
 "vega.vegalite.entry_point_renderer":{
  "__set__":true,
  "elements":[
   "vega-2.3.2-py36_0",
   "vega-2.6.0-py37_0"
  ]
 },
 "vega.widget":{
  "__set__":true,
  "elements":[
   "vega-2.6.0-py37_0"
  ]
 },
 "vega.widget.VegaWidget":{
  "__set__":true,
  "elements":[
   "vega-2.6.0-py37_0"
  ]
 },
 "vega.widget.__all__":{
  "__set__":true,
  "elements":[
   "vega-2.6.0-py37_0"
  ]
 },
 "vega.widget.err":{
  "__set__":true,
  "elements":[
   "vega-2.6.0-py37_0"
  ]
 },
 "vega.widget.new_err":{
  "__set__":true,
  "elements":[
   "vega-2.6.0-py37_0"
  ]
 },
 "versioneer.CONFIG_ERROR":{
  "__set__":true,
  "elements":[
   "diffusioncma-0.5.8-py36h830a2c2_0",
   "diffusioncma-0.5.8-py38hcb8c335_0",
   "splauncher-0.0.9-py35_0"
  ]
 },
 "versioneer.HANDLERS":{
  "__set__":true,
  "elements":[
   "diffusioncma-0.5.8-py36h830a2c2_0",
   "diffusioncma-0.5.8-py38hcb8c335_0",
   "splauncher-0.0.9-py35_0"
  ]
 },
 "versioneer.INIT_PY_SNIPPET":{
  "__set__":true,
  "elements":[
   "diffusioncma-0.5.8-py36h830a2c2_0",
   "diffusioncma-0.5.8-py38hcb8c335_0",
   "splauncher-0.0.9-py35_0"
  ]
 },
 "versioneer.LONG_VERSION_PY":{
  "__set__":true,
  "elements":[
   "diffusioncma-0.5.8-py36h830a2c2_0",
   "diffusioncma-0.5.8-py38hcb8c335_0",
   "splauncher-0.0.9-py35_0"
  ]
 },
 "versioneer.NotThisMethod":{
  "__set__":true,
  "elements":[
   "diffusioncma-0.5.8-py36h830a2c2_0",
   "diffusioncma-0.5.8-py38hcb8c335_0",
   "splauncher-0.0.9-py35_0"
  ]
 },
 "versioneer.SAMPLE_CONFIG":{
  "__set__":true,
  "elements":[
   "diffusioncma-0.5.8-py36h830a2c2_0",
   "diffusioncma-0.5.8-py38hcb8c335_0",
   "splauncher-0.0.9-py35_0"
  ]
 },
 "versioneer.SHORT_VERSION_PY":{
  "__set__":true,
  "elements":[
   "diffusioncma-0.5.8-py36h830a2c2_0",
   "diffusioncma-0.5.8-py38hcb8c335_0",
   "splauncher-0.0.9-py35_0"
  ]
 },
 "versioneer.VERSIONEER_b64":{
  "__set__":true,
  "elements":[
   "versioneer-0.18-py_1"
  ]
 },
 "versioneer.VersioneerBadRootError":{
  "__set__":true,
  "elements":[
   "diffusioncma-0.5.8-py36h830a2c2_0",
   "diffusioncma-0.5.8-py38hcb8c335_0",
   "splauncher-0.0.9-py35_0"
  ]
 },
 "versioneer.VersioneerConfig":{
  "__set__":true,
  "elements":[
   "diffusioncma-0.5.8-py36h830a2c2_0",
   "diffusioncma-0.5.8-py38hcb8c335_0",
   "splauncher-0.0.9-py35_0"
  ]
 },
 "versioneer.cmd":{
  "__set__":true,
  "elements":[
   "diffusioncma-0.5.8-py36h830a2c2_0",
   "diffusioncma-0.5.8-py38hcb8c335_0",
   "splauncher-0.0.9-py35_0"
  ]
 },
 "versioneer.do_setup":{
  "__set__":true,
  "elements":[
   "diffusioncma-0.5.8-py36h830a2c2_0",
   "diffusioncma-0.5.8-py38hcb8c335_0",
   "splauncher-0.0.9-py35_0"
  ]
 },
 "versioneer.do_vcs_install":{
  "__set__":true,
  "elements":[
   "diffusioncma-0.5.8-py36h830a2c2_0",
   "diffusioncma-0.5.8-py38hcb8c335_0",
   "splauncher-0.0.9-py35_0"
  ]
 },
 "versioneer.errors":{
  "__set__":true,
  "elements":[
   "diffusioncma-0.5.8-py36h830a2c2_0",
   "diffusioncma-0.5.8-py38hcb8c335_0",
   "splauncher-0.0.9-py35_0"
  ]
 },
 "versioneer.get_cmdclass":{
  "__set__":true,
  "elements":[
   "diffusioncma-0.5.8-py36h830a2c2_0",
   "diffusioncma-0.5.8-py38hcb8c335_0",
   "splauncher-0.0.9-py35_0"
  ]
 },
 "versioneer.get_config_from_root":{
  "__set__":true,
  "elements":[
   "diffusioncma-0.5.8-py36h830a2c2_0",
   "diffusioncma-0.5.8-py38hcb8c335_0",
   "splauncher-0.0.9-py35_0"
  ]
 },
 "versioneer.get_root":{
  "__set__":true,
  "elements":[
   "diffusioncma-0.5.8-py36h830a2c2_0",
   "diffusioncma-0.5.8-py38hcb8c335_0",
   "splauncher-0.0.9-py35_0"
  ]
 },
 "versioneer.get_version":{
  "__set__":true,
  "elements":[
   "diffusioncma-0.5.8-py36h830a2c2_0",
   "diffusioncma-0.5.8-py38hcb8c335_0",
   "splauncher-0.0.9-py35_0"
  ]
 },
 "versioneer.git_get_keywords":{
  "__set__":true,
  "elements":[
   "diffusioncma-0.5.8-py36h830a2c2_0",
   "diffusioncma-0.5.8-py38hcb8c335_0",
   "splauncher-0.0.9-py35_0"
  ]
 },
 "versioneer.git_pieces_from_vcs":{
  "__set__":true,
  "elements":[
   "diffusioncma-0.5.8-py36h830a2c2_0",
   "diffusioncma-0.5.8-py38hcb8c335_0",
   "splauncher-0.0.9-py35_0"
  ]
 },
 "versioneer.git_versions_from_keywords":{
  "__set__":true,
  "elements":[
   "diffusioncma-0.5.8-py36h830a2c2_0",
   "diffusioncma-0.5.8-py38hcb8c335_0",
   "splauncher-0.0.9-py35_0"
  ]
 },
 "versioneer.main":{
  "__set__":true,
  "elements":[
   "versioneer-0.18-py_1"
  ]
 },
 "versioneer.newver":{
  "__set__":true,
  "elements":[
   "versioneer-0.18-py_1"
  ]
 },
 "versioneer.plus_or_dot":{
  "__set__":true,
  "elements":[
   "diffusioncma-0.5.8-py36h830a2c2_0",
   "diffusioncma-0.5.8-py38hcb8c335_0",
   "splauncher-0.0.9-py35_0"
  ]
 },
 "versioneer.register_vcs_handler":{
  "__set__":true,
  "elements":[
   "diffusioncma-0.5.8-py36h830a2c2_0",
   "diffusioncma-0.5.8-py38hcb8c335_0",
   "splauncher-0.0.9-py35_0"
  ]
 },
 "versioneer.render":{
  "__set__":true,
  "elements":[
   "diffusioncma-0.5.8-py36h830a2c2_0",
   "diffusioncma-0.5.8-py38hcb8c335_0",
   "splauncher-0.0.9-py35_0"
  ]
 },
 "versioneer.run_command":{
  "__set__":true,
  "elements":[
   "diffusioncma-0.5.8-py36h830a2c2_0",
   "diffusioncma-0.5.8-py38hcb8c335_0",
   "splauncher-0.0.9-py35_0"
  ]
 },
 "versioneer.scan_setup_py":{
  "__set__":true,
  "elements":[
   "diffusioncma-0.5.8-py36h830a2c2_0",
   "diffusioncma-0.5.8-py38hcb8c335_0",
   "splauncher-0.0.9-py35_0"
  ]
 },
 "versioneer.versions_from_file":{
  "__set__":true,
  "elements":[
   "diffusioncma-0.5.8-py36h830a2c2_0",
   "diffusioncma-0.5.8-py38hcb8c335_0",
   "splauncher-0.0.9-py35_0"
  ]
 },
 "versioneer.versions_from_parentdir":{
  "__set__":true,
  "elements":[
   "diffusioncma-0.5.8-py36h830a2c2_0",
   "diffusioncma-0.5.8-py38hcb8c335_0",
   "splauncher-0.0.9-py35_0"
  ]
 },
 "versioneer.write_to_version_file":{
  "__set__":true,
  "elements":[
   "diffusioncma-0.5.8-py36h830a2c2_0",
   "diffusioncma-0.5.8-py38hcb8c335_0",
   "splauncher-0.0.9-py35_0"
  ]
 },
 "vertica_python.Connection":{
  "__set__":true,
  "elements":[
   "vertica-python-0.6.13-py35_0",
   "vertica-python-0.6.14-py35_0"
  ]
 },
 "vertica_python.PROTOCOL_VERSION":{
  "__set__":true,
  "elements":[
   "vertica-python-0.6.13-py35_0",
   "vertica-python-0.6.14-py35_0"
  ]
 },
 "vertica_python.__author__":{
  "__set__":true,
  "elements":[
   "vertica-python-0.6.13-py35_0",
   "vertica-python-0.6.14-py35_0"
  ]
 },
 "vertica_python.__copyright__":{
  "__set__":true,
  "elements":[
   "vertica-python-0.6.13-py35_0",
   "vertica-python-0.6.14-py35_0"
  ]
 },
 "vertica_python.__license__":{
  "__set__":true,
  "elements":[
   "vertica-python-0.6.13-py35_0",
   "vertica-python-0.6.14-py35_0"
  ]
 },
 "vertica_python.__version__":{
  "__set__":true,
  "elements":[
   "vertica-python-0.6.13-py35_0",
   "vertica-python-0.6.14-py35_0"
  ]
 },
 "vertica_python.apilevel":{
  "__set__":true,
  "elements":[
   "vertica-python-0.6.13-py35_0",
   "vertica-python-0.6.14-py35_0"
  ]
 },
 "vertica_python.connect":{
  "__set__":true,
  "elements":[
   "vertica-python-0.6.13-py35_0",
   "vertica-python-0.6.14-py35_0"
  ]
 },
 "vertica_python.datatypes":{
  "__set__":true,
  "elements":[
   "vertica-python-0.6.13-py35_0",
   "vertica-python-0.6.14-py35_0"
  ]
 },
 "vertica_python.datatypes.BINARY":{
  "__set__":true,
  "elements":[
   "vertica-python-0.6.13-py35_0",
   "vertica-python-0.6.14-py35_0"
  ]
 },
 "vertica_python.datatypes.Binary":{
  "__set__":true,
  "elements":[
   "vertica-python-0.6.13-py35_0",
   "vertica-python-0.6.14-py35_0"
  ]
 },
 "vertica_python.datatypes.Bytea":{
  "__set__":true,
  "elements":[
   "vertica-python-0.6.13-py35_0",
   "vertica-python-0.6.14-py35_0"
  ]
 },
 "vertica_python.datatypes.DATETIME":{
  "__set__":true,
  "elements":[
   "vertica-python-0.6.13-py35_0",
   "vertica-python-0.6.14-py35_0"
  ]
 },
 "vertica_python.datatypes.Date":{
  "__set__":true,
  "elements":[
   "vertica-python-0.6.13-py35_0",
   "vertica-python-0.6.14-py35_0"
  ]
 },
 "vertica_python.datatypes.NUMBER":{
  "__set__":true,
  "elements":[
   "vertica-python-0.6.13-py35_0",
   "vertica-python-0.6.14-py35_0"
  ]
 },
 "vertica_python.datatypes.ROWID":{
  "__set__":true,
  "elements":[
   "vertica-python-0.6.13-py35_0",
   "vertica-python-0.6.14-py35_0"
  ]
 },
 "vertica_python.datatypes.STRING":{
  "__set__":true,
  "elements":[
   "vertica-python-0.6.13-py35_0",
   "vertica-python-0.6.14-py35_0"
  ]
 },
 "vertica_python.datatypes.Time":{
  "__set__":true,
  "elements":[
   "vertica-python-0.6.13-py35_0",
   "vertica-python-0.6.14-py35_0"
  ]
 },
 "vertica_python.errors":{
  "__set__":true,
  "elements":[
   "vertica-python-0.6.13-py35_0",
   "vertica-python-0.6.14-py35_0"
  ]
 },
 "vertica_python.errors.SSLNotSupported":{
  "__set__":true,
  "elements":[
   "vertica-python-0.6.13-py35_0",
   "vertica-python-0.6.14-py35_0"
  ]
 },
 "vertica_python.paramstyle":{
  "__set__":true,
  "elements":[
   "vertica-python-0.6.13-py35_0",
   "vertica-python-0.6.14-py35_0"
  ]
 },
 "vertica_python.tests":{
  "__set__":true,
  "elements":[
   "vertica-python-0.6.13-py35_0",
   "vertica-python-0.6.14-py35_0"
  ]
 },
 "vertica_python.tests.basic_tests":{
  "__set__":true,
  "elements":[
   "vertica-python-0.6.13-py35_0",
   "vertica-python-0.6.14-py35_0"
  ]
 },
 "vertica_python.tests.basic_tests.TestVerticaPython":{
  "__set__":true,
  "elements":[
   "vertica-python-0.6.13-py35_0",
   "vertica-python-0.6.14-py35_0"
  ]
 },
 "vertica_python.tests.basic_tests.errors":{
  "__set__":true,
  "elements":[
   "vertica-python-0.6.13-py35_0",
   "vertica-python-0.6.14-py35_0"
  ]
 },
 "vertica_python.tests.basic_tests.init_table":{
  "__set__":true,
  "elements":[
   "vertica-python-0.6.13-py35_0",
   "vertica-python-0.6.14-py35_0"
  ]
 },
 "vertica_python.tests.basic_tests.logger":{
  "__set__":true,
  "elements":[
   "vertica-python-0.6.13-py35_0",
   "vertica-python-0.6.14-py35_0"
  ]
 },
 "vertica_python.tests.column_tests":{
  "__set__":true,
  "elements":[
   "vertica-python-0.6.13-py35_0",
   "vertica-python-0.6.14-py35_0"
  ]
 },
 "vertica_python.tests.column_tests.ColumnTestCase":{
  "__set__":true,
  "elements":[
   "vertica-python-0.6.13-py35_0",
   "vertica-python-0.6.14-py35_0"
  ]
 },
 "vertica_python.tests.date_tests":{
  "__set__":true,
  "elements":[
   "vertica-python-0.6.13-py35_0",
   "vertica-python-0.6.14-py35_0"
  ]
 },
 "vertica_python.tests.date_tests.DateParsingTestCase":{
  "__set__":true,
  "elements":[
   "vertica-python-0.6.13-py35_0",
   "vertica-python-0.6.14-py35_0"
  ]
 },
 "vertica_python.tests.date_tests.TimestampParsingTestCase":{
  "__set__":true,
  "elements":[
   "vertica-python-0.6.13-py35_0",
   "vertica-python-0.6.14-py35_0"
  ]
 },
 "vertica_python.tests.date_tests.VerticaTestCase":{
  "__set__":true,
  "elements":[
   "vertica-python-0.6.13-py35_0",
   "vertica-python-0.6.14-py35_0"
  ]
 },
 "vertica_python.tests.date_tests.conn_info":{
  "__set__":true,
  "elements":[
   "vertica-python-0.6.13-py35_0",
   "vertica-python-0.6.14-py35_0"
  ]
 },
 "vertica_python.tests.date_tests.errors":{
  "__set__":true,
  "elements":[
   "vertica-python-0.6.13-py35_0",
   "vertica-python-0.6.14-py35_0"
  ]
 },
 "vertica_python.tests.date_tests.timestamp_parse":{
  "__set__":true,
  "elements":[
   "vertica-python-0.6.13-py35_0",
   "vertica-python-0.6.14-py35_0"
  ]
 },
 "vertica_python.tests.error_tests":{
  "__set__":true,
  "elements":[
   "vertica-python-0.6.13-py35_0",
   "vertica-python-0.6.14-py35_0"
  ]
 },
 "vertica_python.tests.error_tests.ErrorTestCase":{
  "__set__":true,
  "elements":[
   "vertica-python-0.6.13-py35_0",
   "vertica-python-0.6.14-py35_0"
  ]
 },
 "vertica_python.tests.test_commons":{
  "__set__":true,
  "elements":[
   "vertica-python-0.6.13-py35_0",
   "vertica-python-0.6.14-py35_0"
  ]
 },
 "vertica_python.tests.test_commons.VerticaTestCase":{
  "__set__":true,
  "elements":[
   "vertica-python-0.6.13-py35_0",
   "vertica-python-0.6.14-py35_0"
  ]
 },
 "vertica_python.tests.test_commons.conn_info":{
  "__set__":true,
  "elements":[
   "vertica-python-0.6.13-py35_0",
   "vertica-python-0.6.14-py35_0"
  ]
 },
 "vertica_python.tests.timezone_tests":{
  "__set__":true,
  "elements":[
   "vertica-python-0.6.13-py35_0",
   "vertica-python-0.6.14-py35_0"
  ]
 },
 "vertica_python.tests.timezone_tests.TimeZoneTestCase":{
  "__set__":true,
  "elements":[
   "vertica-python-0.6.13-py35_0",
   "vertica-python-0.6.14-py35_0"
  ]
 },
 "vertica_python.tests.type_tests":{
  "__set__":true,
  "elements":[
   "vertica-python-0.6.13-py35_0",
   "vertica-python-0.6.14-py35_0"
  ]
 },
 "vertica_python.tests.type_tests.TypeTestCase":{
  "__set__":true,
  "elements":[
   "vertica-python-0.6.13-py35_0",
   "vertica-python-0.6.14-py35_0"
  ]
 },
 "vertica_python.tests.unicode_tests":{
  "__set__":true,
  "elements":[
   "vertica-python-0.6.13-py35_0",
   "vertica-python-0.6.14-py35_0"
  ]
 },
 "vertica_python.tests.unicode_tests.UnicodeTestCase":{
  "__set__":true,
  "elements":[
   "vertica-python-0.6.13-py35_0",
   "vertica-python-0.6.14-py35_0"
  ]
 },
 "vertica_python.threadsafety":{
  "__set__":true,
  "elements":[
   "vertica-python-0.6.13-py35_0",
   "vertica-python-0.6.14-py35_0"
  ]
 },
 "vertica_python.version_info":{
  "__set__":true,
  "elements":[
   "vertica-python-0.6.13-py35_0",
   "vertica-python-0.6.14-py35_0"
  ]
 },
 "vertica_python.vertica":{
  "__set__":true,
  "elements":[
   "vertica-python-0.6.13-py35_0",
   "vertica-python-0.6.14-py35_0"
  ]
 },
 "vertica_python.vertica.column":{
  "__set__":true,
  "elements":[
   "vertica-python-0.6.13-py35_0",
   "vertica-python-0.6.14-py35_0"
  ]
 },
 "vertica_python.vertica.column.Column":{
  "__set__":true,
  "elements":[
   "vertica-python-0.6.13-py35_0",
   "vertica-python-0.6.14-py35_0"
  ]
 },
 "vertica_python.vertica.column._timestamp_parse":{
  "__set__":true,
  "elements":[
   "vertica-python-0.6.13-py35_0",
   "vertica-python-0.6.14-py35_0"
  ]
 },
 "vertica_python.vertica.column.date_parse":{
  "__set__":true,
  "elements":[
   "vertica-python-0.6.13-py35_0",
   "vertica-python-0.6.14-py35_0"
  ]
 },
 "vertica_python.vertica.column.errors":{
  "__set__":true,
  "elements":[
   "vertica-python-0.6.13-py35_0",
   "vertica-python-0.6.14-py35_0"
  ]
 },
 "vertica_python.vertica.column.timestamp_parse":{
  "__set__":true,
  "elements":[
   "vertica-python-0.6.13-py35_0",
   "vertica-python-0.6.14-py35_0"
  ]
 },
 "vertica_python.vertica.column.timestamp_tz_parse":{
  "__set__":true,
  "elements":[
   "vertica-python-0.6.13-py35_0",
   "vertica-python-0.6.14-py35_0"
  ]
 },
 "vertica_python.vertica.column.years_re":{
  "__set__":true,
  "elements":[
   "vertica-python-0.6.13-py35_0",
   "vertica-python-0.6.14-py35_0"
  ]
 },
 "vertica_python.vertica.connection":{
  "__set__":true,
  "elements":[
   "vertica-python-0.6.13-py35_0",
   "vertica-python-0.6.14-py35_0"
  ]
 },
 "vertica_python.vertica.connection.BackendMessage":{
  "__set__":true,
  "elements":[
   "vertica-python-0.6.13-py35_0",
   "vertica-python-0.6.14-py35_0"
  ]
 },
 "vertica_python.vertica.connection.Connection":{
  "__set__":true,
  "elements":[
   "vertica-python-0.6.13-py35_0",
   "vertica-python-0.6.14-py35_0"
  ]
 },
 "vertica_python.vertica.connection.Cursor":{
  "__set__":true,
  "elements":[
   "vertica-python-0.6.13-py35_0",
   "vertica-python-0.6.14-py35_0"
  ]
 },
 "vertica_python.vertica.connection.SSLNotSupported":{
  "__set__":true,
  "elements":[
   "vertica-python-0.6.13-py35_0",
   "vertica-python-0.6.14-py35_0"
  ]
 },
 "vertica_python.vertica.connection.errors":{
  "__set__":true,
  "elements":[
   "vertica-python-0.6.13-py35_0",
   "vertica-python-0.6.14-py35_0"
  ]
 },
 "vertica_python.vertica.connection.logger":{
  "__set__":true,
  "elements":[
   "vertica-python-0.6.13-py35_0",
   "vertica-python-0.6.14-py35_0"
  ]
 },
 "vertica_python.vertica.connection.messages":{
  "__set__":true,
  "elements":[
   "vertica-python-0.6.13-py35_0",
   "vertica-python-0.6.14-py35_0"
  ]
 },
 "vertica_python.vertica.cursor":{
  "__set__":true,
  "elements":[
   "vertica-python-0.6.13-py35_0",
   "vertica-python-0.6.14-py35_0"
  ]
 },
 "vertica_python.vertica.cursor.Column":{
  "__set__":true,
  "elements":[
   "vertica-python-0.6.13-py35_0",
   "vertica-python-0.6.14-py35_0"
  ]
 },
 "vertica_python.vertica.cursor.Cursor":{
  "__set__":true,
  "elements":[
   "vertica-python-0.6.13-py35_0",
   "vertica-python-0.6.14-py35_0"
  ]
 },
 "vertica_python.vertica.cursor.errors":{
  "__set__":true,
  "elements":[
   "vertica-python-0.6.13-py35_0",
   "vertica-python-0.6.14-py35_0"
  ]
 },
 "vertica_python.vertica.cursor.logger":{
  "__set__":true,
  "elements":[
   "vertica-python-0.6.13-py35_0",
   "vertica-python-0.6.14-py35_0"
  ]
 },
 "vertica_python.vertica.cursor.messages":{
  "__set__":true,
  "elements":[
   "vertica-python-0.6.13-py35_0",
   "vertica-python-0.6.14-py35_0"
  ]
 },
 "vertica_python.vertica.messages":{
  "__set__":true,
  "elements":[
   "vertica-python-0.6.13-py35_0",
   "vertica-python-0.6.14-py35_0"
  ]
 },
 "vertica_python.vertica.messages.Authentication":{
  "__set__":true,
  "elements":[
   "vertica-python-0.6.13-py35_0",
   "vertica-python-0.6.14-py35_0"
  ]
 },
 "vertica_python.vertica.messages.BackendKeyData":{
  "__set__":true,
  "elements":[
   "vertica-python-0.6.13-py35_0",
   "vertica-python-0.6.14-py35_0"
  ]
 },
 "vertica_python.vertica.messages.Bind":{
  "__set__":true,
  "elements":[
   "vertica-python-0.6.13-py35_0",
   "vertica-python-0.6.14-py35_0"
  ]
 },
 "vertica_python.vertica.messages.CancelRequest":{
  "__set__":true,
  "elements":[
   "vertica-python-0.6.13-py35_0",
   "vertica-python-0.6.14-py35_0"
  ]
 },
 "vertica_python.vertica.messages.Close":{
  "__set__":true,
  "elements":[
   "vertica-python-0.6.13-py35_0",
   "vertica-python-0.6.14-py35_0"
  ]
 },
 "vertica_python.vertica.messages.CommandComplete":{
  "__set__":true,
  "elements":[
   "vertica-python-0.6.13-py35_0",
   "vertica-python-0.6.14-py35_0"
  ]
 },
 "vertica_python.vertica.messages.CopyData":{
  "__set__":true,
  "elements":[
   "vertica-python-0.6.13-py35_0",
   "vertica-python-0.6.14-py35_0"
  ]
 },
 "vertica_python.vertica.messages.CopyDone":{
  "__set__":true,
  "elements":[
   "vertica-python-0.6.13-py35_0",
   "vertica-python-0.6.14-py35_0"
  ]
 },
 "vertica_python.vertica.messages.CopyFail":{
  "__set__":true,
  "elements":[
   "vertica-python-0.6.13-py35_0",
   "vertica-python-0.6.14-py35_0"
  ]
 },
 "vertica_python.vertica.messages.CopyInResponse":{
  "__set__":true,
  "elements":[
   "vertica-python-0.6.13-py35_0",
   "vertica-python-0.6.14-py35_0"
  ]
 },
 "vertica_python.vertica.messages.CopyStream":{
  "__set__":true,
  "elements":[
   "vertica-python-0.6.13-py35_0",
   "vertica-python-0.6.14-py35_0"
  ]
 },
 "vertica_python.vertica.messages.DataRow":{
  "__set__":true,
  "elements":[
   "vertica-python-0.6.13-py35_0",
   "vertica-python-0.6.14-py35_0"
  ]
 },
 "vertica_python.vertica.messages.Describe":{
  "__set__":true,
  "elements":[
   "vertica-python-0.6.13-py35_0",
   "vertica-python-0.6.14-py35_0"
  ]
 },
 "vertica_python.vertica.messages.EmptyQueryResponse":{
  "__set__":true,
  "elements":[
   "vertica-python-0.6.13-py35_0",
   "vertica-python-0.6.14-py35_0"
  ]
 },
 "vertica_python.vertica.messages.ErrorResponse":{
  "__set__":true,
  "elements":[
   "vertica-python-0.6.13-py35_0",
   "vertica-python-0.6.14-py35_0"
  ]
 },
 "vertica_python.vertica.messages.Execute":{
  "__set__":true,
  "elements":[
   "vertica-python-0.6.13-py35_0",
   "vertica-python-0.6.14-py35_0"
  ]
 },
 "vertica_python.vertica.messages.Flush":{
  "__set__":true,
  "elements":[
   "vertica-python-0.6.13-py35_0",
   "vertica-python-0.6.14-py35_0"
  ]
 },
 "vertica_python.vertica.messages.NoData":{
  "__set__":true,
  "elements":[
   "vertica-python-0.6.13-py35_0",
   "vertica-python-0.6.14-py35_0"
  ]
 },
 "vertica_python.vertica.messages.NoticeResponse":{
  "__set__":true,
  "elements":[
   "vertica-python-0.6.13-py35_0",
   "vertica-python-0.6.14-py35_0"
  ]
 },
 "vertica_python.vertica.messages.ParameterDescription":{
  "__set__":true,
  "elements":[
   "vertica-python-0.6.13-py35_0",
   "vertica-python-0.6.14-py35_0"
  ]
 },
 "vertica_python.vertica.messages.ParameterStatus":{
  "__set__":true,
  "elements":[
   "vertica-python-0.6.13-py35_0",
   "vertica-python-0.6.14-py35_0"
  ]
 },
 "vertica_python.vertica.messages.Parse":{
  "__set__":true,
  "elements":[
   "vertica-python-0.6.13-py35_0",
   "vertica-python-0.6.14-py35_0"
  ]
 },
 "vertica_python.vertica.messages.Password":{
  "__set__":true,
  "elements":[
   "vertica-python-0.6.13-py35_0",
   "vertica-python-0.6.14-py35_0"
  ]
 },
 "vertica_python.vertica.messages.PortalSuspended":{
  "__set__":true,
  "elements":[
   "vertica-python-0.6.13-py35_0",
   "vertica-python-0.6.14-py35_0"
  ]
 },
 "vertica_python.vertica.messages.Query":{
  "__set__":true,
  "elements":[
   "vertica-python-0.6.13-py35_0",
   "vertica-python-0.6.14-py35_0"
  ]
 },
 "vertica_python.vertica.messages.ReadyForQuery":{
  "__set__":true,
  "elements":[
   "vertica-python-0.6.13-py35_0",
   "vertica-python-0.6.14-py35_0"
  ]
 },
 "vertica_python.vertica.messages.RowDescription":{
  "__set__":true,
  "elements":[
   "vertica-python-0.6.13-py35_0",
   "vertica-python-0.6.14-py35_0"
  ]
 },
 "vertica_python.vertica.messages.SslRequest":{
  "__set__":true,
  "elements":[
   "vertica-python-0.6.13-py35_0",
   "vertica-python-0.6.14-py35_0"
  ]
 },
 "vertica_python.vertica.messages.Startup":{
  "__set__":true,
  "elements":[
   "vertica-python-0.6.13-py35_0",
   "vertica-python-0.6.14-py35_0"
  ]
 },
 "vertica_python.vertica.messages.Sync":{
  "__set__":true,
  "elements":[
   "vertica-python-0.6.13-py35_0",
   "vertica-python-0.6.14-py35_0"
  ]
 },
 "vertica_python.vertica.messages.Terminate":{
  "__set__":true,
  "elements":[
   "vertica-python-0.6.13-py35_0",
   "vertica-python-0.6.14-py35_0"
  ]
 },
 "vertica_python.vertica.messages.Unknown":{
  "__set__":true,
  "elements":[
   "vertica-python-0.6.13-py35_0",
   "vertica-python-0.6.14-py35_0"
  ]
 },
 "vertica_python.vertica.messages.__all__":{
  "__set__":true,
  "elements":[
   "vertica-python-0.6.13-py35_0",
   "vertica-python-0.6.14-py35_0"
  ]
 },
 "vertica_python.vertica.messages.backend_messages":{
  "__set__":true,
  "elements":[
   "vertica-python-0.6.13-py35_0",
   "vertica-python-0.6.14-py35_0"
  ]
 },
 "vertica_python.vertica.messages.backend_messages.authentication":{
  "__set__":true,
  "elements":[
   "vertica-python-0.6.13-py35_0",
   "vertica-python-0.6.14-py35_0"
  ]
 },
 "vertica_python.vertica.messages.backend_messages.authentication.Authentication":{
  "__set__":true,
  "elements":[
   "vertica-python-0.6.13-py35_0",
   "vertica-python-0.6.14-py35_0"
  ]
 },
 "vertica_python.vertica.messages.backend_messages.authentication.BackendMessage":{
  "__set__":true,
  "elements":[
   "vertica-python-0.6.13-py35_0",
   "vertica-python-0.6.14-py35_0"
  ]
 },
 "vertica_python.vertica.messages.backend_messages.backend_key_data":{
  "__set__":true,
  "elements":[
   "vertica-python-0.6.13-py35_0",
   "vertica-python-0.6.14-py35_0"
  ]
 },
 "vertica_python.vertica.messages.backend_messages.backend_key_data.BackendKeyData":{
  "__set__":true,
  "elements":[
   "vertica-python-0.6.13-py35_0",
   "vertica-python-0.6.14-py35_0"
  ]
 },
 "vertica_python.vertica.messages.backend_messages.backend_key_data.BackendMessage":{
  "__set__":true,
  "elements":[
   "vertica-python-0.6.13-py35_0",
   "vertica-python-0.6.14-py35_0"
  ]
 },
 "vertica_python.vertica.messages.backend_messages.bind_complete":{
  "__set__":true,
  "elements":[
   "vertica-python-0.6.13-py35_0",
   "vertica-python-0.6.14-py35_0"
  ]
 },
 "vertica_python.vertica.messages.backend_messages.bind_complete.BackendMessage":{
  "__set__":true,
  "elements":[
   "vertica-python-0.6.13-py35_0",
   "vertica-python-0.6.14-py35_0"
  ]
 },
 "vertica_python.vertica.messages.backend_messages.bind_complete.BindComplete":{
  "__set__":true,
  "elements":[
   "vertica-python-0.6.13-py35_0",
   "vertica-python-0.6.14-py35_0"
  ]
 },
 "vertica_python.vertica.messages.backend_messages.close_complete":{
  "__set__":true,
  "elements":[
   "vertica-python-0.6.13-py35_0",
   "vertica-python-0.6.14-py35_0"
  ]
 },
 "vertica_python.vertica.messages.backend_messages.close_complete.BackendMessage":{
  "__set__":true,
  "elements":[
   "vertica-python-0.6.13-py35_0",
   "vertica-python-0.6.14-py35_0"
  ]
 },
 "vertica_python.vertica.messages.backend_messages.close_complete.CloseComplete":{
  "__set__":true,
  "elements":[
   "vertica-python-0.6.13-py35_0",
   "vertica-python-0.6.14-py35_0"
  ]
 },
 "vertica_python.vertica.messages.backend_messages.command_complete":{
  "__set__":true,
  "elements":[
   "vertica-python-0.6.13-py35_0",
   "vertica-python-0.6.14-py35_0"
  ]
 },
 "vertica_python.vertica.messages.backend_messages.command_complete.BackendMessage":{
  "__set__":true,
  "elements":[
   "vertica-python-0.6.13-py35_0",
   "vertica-python-0.6.14-py35_0"
  ]
 },
 "vertica_python.vertica.messages.backend_messages.command_complete.CommandComplete":{
  "__set__":true,
  "elements":[
   "vertica-python-0.6.13-py35_0",
   "vertica-python-0.6.14-py35_0"
  ]
 },
 "vertica_python.vertica.messages.backend_messages.copy_in_response":{
  "__set__":true,
  "elements":[
   "vertica-python-0.6.13-py35_0",
   "vertica-python-0.6.14-py35_0"
  ]
 },
 "vertica_python.vertica.messages.backend_messages.copy_in_response.BackendMessage":{
  "__set__":true,
  "elements":[
   "vertica-python-0.6.13-py35_0",
   "vertica-python-0.6.14-py35_0"
  ]
 },
 "vertica_python.vertica.messages.backend_messages.copy_in_response.CopyInResponse":{
  "__set__":true,
  "elements":[
   "vertica-python-0.6.13-py35_0",
   "vertica-python-0.6.14-py35_0"
  ]
 },
 "vertica_python.vertica.messages.backend_messages.data_row":{
  "__set__":true,
  "elements":[
   "vertica-python-0.6.13-py35_0",
   "vertica-python-0.6.14-py35_0"
  ]
 },
 "vertica_python.vertica.messages.backend_messages.data_row.BackendMessage":{
  "__set__":true,
  "elements":[
   "vertica-python-0.6.13-py35_0",
   "vertica-python-0.6.14-py35_0"
  ]
 },
 "vertica_python.vertica.messages.backend_messages.data_row.DataRow":{
  "__set__":true,
  "elements":[
   "vertica-python-0.6.13-py35_0",
   "vertica-python-0.6.14-py35_0"
  ]
 },
 "vertica_python.vertica.messages.backend_messages.empty_query_response":{
  "__set__":true,
  "elements":[
   "vertica-python-0.6.13-py35_0",
   "vertica-python-0.6.14-py35_0"
  ]
 },
 "vertica_python.vertica.messages.backend_messages.empty_query_response.BackendMessage":{
  "__set__":true,
  "elements":[
   "vertica-python-0.6.13-py35_0",
   "vertica-python-0.6.14-py35_0"
  ]
 },
 "vertica_python.vertica.messages.backend_messages.empty_query_response.EmptyQueryResponse":{
  "__set__":true,
  "elements":[
   "vertica-python-0.6.13-py35_0",
   "vertica-python-0.6.14-py35_0"
  ]
 },
 "vertica_python.vertica.messages.backend_messages.error_response":{
  "__set__":true,
  "elements":[
   "vertica-python-0.6.13-py35_0",
   "vertica-python-0.6.14-py35_0"
  ]
 },
 "vertica_python.vertica.messages.backend_messages.error_response.BackendMessage":{
  "__set__":true,
  "elements":[
   "vertica-python-0.6.13-py35_0",
   "vertica-python-0.6.14-py35_0"
  ]
 },
 "vertica_python.vertica.messages.backend_messages.error_response.ErrorResponse":{
  "__set__":true,
  "elements":[
   "vertica-python-0.6.13-py35_0",
   "vertica-python-0.6.14-py35_0"
  ]
 },
 "vertica_python.vertica.messages.backend_messages.error_response.NoticeResponse":{
  "__set__":true,
  "elements":[
   "vertica-python-0.6.13-py35_0",
   "vertica-python-0.6.14-py35_0"
  ]
 },
 "vertica_python.vertica.messages.backend_messages.no_data":{
  "__set__":true,
  "elements":[
   "vertica-python-0.6.13-py35_0",
   "vertica-python-0.6.14-py35_0"
  ]
 },
 "vertica_python.vertica.messages.backend_messages.no_data.BackendMessage":{
  "__set__":true,
  "elements":[
   "vertica-python-0.6.13-py35_0",
   "vertica-python-0.6.14-py35_0"
  ]
 },
 "vertica_python.vertica.messages.backend_messages.no_data.NoData":{
  "__set__":true,
  "elements":[
   "vertica-python-0.6.13-py35_0",
   "vertica-python-0.6.14-py35_0"
  ]
 },
 "vertica_python.vertica.messages.backend_messages.notice_response":{
  "__set__":true,
  "elements":[
   "vertica-python-0.6.13-py35_0",
   "vertica-python-0.6.14-py35_0"
  ]
 },
 "vertica_python.vertica.messages.backend_messages.notice_response.BackendMessage":{
  "__set__":true,
  "elements":[
   "vertica-python-0.6.13-py35_0",
   "vertica-python-0.6.14-py35_0"
  ]
 },
 "vertica_python.vertica.messages.backend_messages.notice_response.NoticeResponse":{
  "__set__":true,
  "elements":[
   "vertica-python-0.6.13-py35_0",
   "vertica-python-0.6.14-py35_0"
  ]
 },
 "vertica_python.vertica.messages.backend_messages.parameter_description":{
  "__set__":true,
  "elements":[
   "vertica-python-0.6.13-py35_0",
   "vertica-python-0.6.14-py35_0"
  ]
 },
 "vertica_python.vertica.messages.backend_messages.parameter_description.BackendMessage":{
  "__set__":true,
  "elements":[
   "vertica-python-0.6.13-py35_0",
   "vertica-python-0.6.14-py35_0"
  ]
 },
 "vertica_python.vertica.messages.backend_messages.parameter_description.Column":{
  "__set__":true,
  "elements":[
   "vertica-python-0.6.13-py35_0",
   "vertica-python-0.6.14-py35_0"
  ]
 },
 "vertica_python.vertica.messages.backend_messages.parameter_description.ParameterDescription":{
  "__set__":true,
  "elements":[
   "vertica-python-0.6.13-py35_0",
   "vertica-python-0.6.14-py35_0"
  ]
 },
 "vertica_python.vertica.messages.backend_messages.parameter_status":{
  "__set__":true,
  "elements":[
   "vertica-python-0.6.13-py35_0",
   "vertica-python-0.6.14-py35_0"
  ]
 },
 "vertica_python.vertica.messages.backend_messages.parameter_status.BackendMessage":{
  "__set__":true,
  "elements":[
   "vertica-python-0.6.13-py35_0",
   "vertica-python-0.6.14-py35_0"
  ]
 },
 "vertica_python.vertica.messages.backend_messages.parameter_status.ParameterStatus":{
  "__set__":true,
  "elements":[
   "vertica-python-0.6.13-py35_0",
   "vertica-python-0.6.14-py35_0"
  ]
 },
 "vertica_python.vertica.messages.backend_messages.parse_complete":{
  "__set__":true,
  "elements":[
   "vertica-python-0.6.13-py35_0",
   "vertica-python-0.6.14-py35_0"
  ]
 },
 "vertica_python.vertica.messages.backend_messages.parse_complete.BackendMessage":{
  "__set__":true,
  "elements":[
   "vertica-python-0.6.13-py35_0",
   "vertica-python-0.6.14-py35_0"
  ]
 },
 "vertica_python.vertica.messages.backend_messages.parse_complete.ParseComplete":{
  "__set__":true,
  "elements":[
   "vertica-python-0.6.13-py35_0",
   "vertica-python-0.6.14-py35_0"
  ]
 },
 "vertica_python.vertica.messages.backend_messages.portal_suspended":{
  "__set__":true,
  "elements":[
   "vertica-python-0.6.13-py35_0",
   "vertica-python-0.6.14-py35_0"
  ]
 },
 "vertica_python.vertica.messages.backend_messages.portal_suspended.BackendMessage":{
  "__set__":true,
  "elements":[
   "vertica-python-0.6.13-py35_0",
   "vertica-python-0.6.14-py35_0"
  ]
 },
 "vertica_python.vertica.messages.backend_messages.portal_suspended.PortalSuspended":{
  "__set__":true,
  "elements":[
   "vertica-python-0.6.13-py35_0",
   "vertica-python-0.6.14-py35_0"
  ]
 },
 "vertica_python.vertica.messages.backend_messages.ready_for_query":{
  "__set__":true,
  "elements":[
   "vertica-python-0.6.13-py35_0",
   "vertica-python-0.6.14-py35_0"
  ]
 },
 "vertica_python.vertica.messages.backend_messages.ready_for_query.BackendMessage":{
  "__set__":true,
  "elements":[
   "vertica-python-0.6.13-py35_0",
   "vertica-python-0.6.14-py35_0"
  ]
 },
 "vertica_python.vertica.messages.backend_messages.ready_for_query.ReadyForQuery":{
  "__set__":true,
  "elements":[
   "vertica-python-0.6.13-py35_0",
   "vertica-python-0.6.14-py35_0"
  ]
 },
 "vertica_python.vertica.messages.backend_messages.row_description":{
  "__set__":true,
  "elements":[
   "vertica-python-0.6.13-py35_0",
   "vertica-python-0.6.14-py35_0"
  ]
 },
 "vertica_python.vertica.messages.backend_messages.row_description.BackendMessage":{
  "__set__":true,
  "elements":[
   "vertica-python-0.6.13-py35_0",
   "vertica-python-0.6.14-py35_0"
  ]
 },
 "vertica_python.vertica.messages.backend_messages.row_description.RowDescription":{
  "__set__":true,
  "elements":[
   "vertica-python-0.6.13-py35_0",
   "vertica-python-0.6.14-py35_0"
  ]
 },
 "vertica_python.vertica.messages.backend_messages.unknown":{
  "__set__":true,
  "elements":[
   "vertica-python-0.6.13-py35_0",
   "vertica-python-0.6.14-py35_0"
  ]
 },
 "vertica_python.vertica.messages.backend_messages.unknown.BackendMessage":{
  "__set__":true,
  "elements":[
   "vertica-python-0.6.13-py35_0",
   "vertica-python-0.6.14-py35_0"
  ]
 },
 "vertica_python.vertica.messages.backend_messages.unknown.Unknown":{
  "__set__":true,
  "elements":[
   "vertica-python-0.6.13-py35_0",
   "vertica-python-0.6.14-py35_0"
  ]
 },
 "vertica_python.vertica.messages.frontend_messages":{
  "__set__":true,
  "elements":[
   "vertica-python-0.6.13-py35_0",
   "vertica-python-0.6.14-py35_0"
  ]
 },
 "vertica_python.vertica.messages.frontend_messages.bind":{
  "__set__":true,
  "elements":[
   "vertica-python-0.6.13-py35_0",
   "vertica-python-0.6.14-py35_0"
  ]
 },
 "vertica_python.vertica.messages.frontend_messages.bind.Bind":{
  "__set__":true,
  "elements":[
   "vertica-python-0.6.13-py35_0",
   "vertica-python-0.6.14-py35_0"
  ]
 },
 "vertica_python.vertica.messages.frontend_messages.bind.FrontendMessage":{
  "__set__":true,
  "elements":[
   "vertica-python-0.6.13-py35_0",
   "vertica-python-0.6.14-py35_0"
  ]
 },
 "vertica_python.vertica.messages.frontend_messages.cancel_request":{
  "__set__":true,
  "elements":[
   "vertica-python-0.6.13-py35_0",
   "vertica-python-0.6.14-py35_0"
  ]
 },
 "vertica_python.vertica.messages.frontend_messages.cancel_request.CancelRequest":{
  "__set__":true,
  "elements":[
   "vertica-python-0.6.13-py35_0",
   "vertica-python-0.6.14-py35_0"
  ]
 },
 "vertica_python.vertica.messages.frontend_messages.cancel_request.FrontendMessage":{
  "__set__":true,
  "elements":[
   "vertica-python-0.6.13-py35_0",
   "vertica-python-0.6.14-py35_0"
  ]
 },
 "vertica_python.vertica.messages.frontend_messages.close":{
  "__set__":true,
  "elements":[
   "vertica-python-0.6.13-py35_0",
   "vertica-python-0.6.14-py35_0"
  ]
 },
 "vertica_python.vertica.messages.frontend_messages.close.Close":{
  "__set__":true,
  "elements":[
   "vertica-python-0.6.13-py35_0",
   "vertica-python-0.6.14-py35_0"
  ]
 },
 "vertica_python.vertica.messages.frontend_messages.close.FrontendMessage":{
  "__set__":true,
  "elements":[
   "vertica-python-0.6.13-py35_0",
   "vertica-python-0.6.14-py35_0"
  ]
 },
 "vertica_python.vertica.messages.frontend_messages.copy_data":{
  "__set__":true,
  "elements":[
   "vertica-python-0.6.13-py35_0",
   "vertica-python-0.6.14-py35_0"
  ]
 },
 "vertica_python.vertica.messages.frontend_messages.copy_data.CopyData":{
  "__set__":true,
  "elements":[
   "vertica-python-0.6.13-py35_0",
   "vertica-python-0.6.14-py35_0"
  ]
 },
 "vertica_python.vertica.messages.frontend_messages.copy_data.FrontendMessage":{
  "__set__":true,
  "elements":[
   "vertica-python-0.6.13-py35_0",
   "vertica-python-0.6.14-py35_0"
  ]
 },
 "vertica_python.vertica.messages.frontend_messages.copy_done":{
  "__set__":true,
  "elements":[
   "vertica-python-0.6.13-py35_0",
   "vertica-python-0.6.14-py35_0"
  ]
 },
 "vertica_python.vertica.messages.frontend_messages.copy_done.CopyDone":{
  "__set__":true,
  "elements":[
   "vertica-python-0.6.13-py35_0",
   "vertica-python-0.6.14-py35_0"
  ]
 },
 "vertica_python.vertica.messages.frontend_messages.copy_done.FrontendMessage":{
  "__set__":true,
  "elements":[
   "vertica-python-0.6.13-py35_0",
   "vertica-python-0.6.14-py35_0"
  ]
 },
 "vertica_python.vertica.messages.frontend_messages.copy_fail":{
  "__set__":true,
  "elements":[
   "vertica-python-0.6.13-py35_0",
   "vertica-python-0.6.14-py35_0"
  ]
 },
 "vertica_python.vertica.messages.frontend_messages.copy_fail.CopyFail":{
  "__set__":true,
  "elements":[
   "vertica-python-0.6.13-py35_0",
   "vertica-python-0.6.14-py35_0"
  ]
 },
 "vertica_python.vertica.messages.frontend_messages.copy_fail.FrontendMessage":{
  "__set__":true,
  "elements":[
   "vertica-python-0.6.13-py35_0",
   "vertica-python-0.6.14-py35_0"
  ]
 },
 "vertica_python.vertica.messages.frontend_messages.copy_stream":{
  "__set__":true,
  "elements":[
   "vertica-python-0.6.13-py35_0",
   "vertica-python-0.6.14-py35_0"
  ]
 },
 "vertica_python.vertica.messages.frontend_messages.copy_stream.CopyStream":{
  "__set__":true,
  "elements":[
   "vertica-python-0.6.13-py35_0",
   "vertica-python-0.6.14-py35_0"
  ]
 },
 "vertica_python.vertica.messages.frontend_messages.copy_stream.FrontendMessage":{
  "__set__":true,
  "elements":[
   "vertica-python-0.6.13-py35_0",
   "vertica-python-0.6.14-py35_0"
  ]
 },
 "vertica_python.vertica.messages.frontend_messages.crypt_windows":{
  "__set__":true,
  "elements":[
   "vertica-python-0.6.13-py35_0",
   "vertica-python-0.6.14-py35_0"
  ]
 },
 "vertica_python.vertica.messages.frontend_messages.crypt_windows.C":{
  "__set__":true,
  "elements":[
   "vertica-python-0.6.13-py35_0",
   "vertica-python-0.6.14-py35_0"
  ]
 },
 "vertica_python.vertica.messages.frontend_messages.crypt_windows.D":{
  "__set__":true,
  "elements":[
   "vertica-python-0.6.13-py35_0",
   "vertica-python-0.6.14-py35_0"
  ]
 },
 "vertica_python.vertica.messages.frontend_messages.crypt_windows.FP":{
  "__set__":true,
  "elements":[
   "vertica-python-0.6.13-py35_0",
   "vertica-python-0.6.14-py35_0"
  ]
 },
 "vertica_python.vertica.messages.frontend_messages.crypt_windows.IP":{
  "__set__":true,
  "elements":[
   "vertica-python-0.6.13-py35_0",
   "vertica-python-0.6.14-py35_0"
  ]
 },
 "vertica_python.vertica.messages.frontend_messages.crypt_windows.KS":{
  "__set__":true,
  "elements":[
   "vertica-python-0.6.13-py35_0",
   "vertica-python-0.6.14-py35_0"
  ]
 },
 "vertica_python.vertica.messages.frontend_messages.crypt_windows.P":{
  "__set__":true,
  "elements":[
   "vertica-python-0.6.13-py35_0",
   "vertica-python-0.6.14-py35_0"
  ]
 },
 "vertica_python.vertica.messages.frontend_messages.crypt_windows.PC1_C":{
  "__set__":true,
  "elements":[
   "vertica-python-0.6.13-py35_0",
   "vertica-python-0.6.14-py35_0"
  ]
 },
 "vertica_python.vertica.messages.frontend_messages.crypt_windows.PC1_D":{
  "__set__":true,
  "elements":[
   "vertica-python-0.6.13-py35_0",
   "vertica-python-0.6.14-py35_0"
  ]
 },
 "vertica_python.vertica.messages.frontend_messages.crypt_windows.PC2_C":{
  "__set__":true,
  "elements":[
   "vertica-python-0.6.13-py35_0",
   "vertica-python-0.6.14-py35_0"
  ]
 },
 "vertica_python.vertica.messages.frontend_messages.crypt_windows.PC2_D":{
  "__set__":true,
  "elements":[
   "vertica-python-0.6.13-py35_0",
   "vertica-python-0.6.14-py35_0"
  ]
 },
 "vertica_python.vertica.messages.frontend_messages.crypt_windows.S":{
  "__set__":true,
  "elements":[
   "vertica-python-0.6.13-py35_0",
   "vertica-python-0.6.14-py35_0"
  ]
 },
 "vertica_python.vertica.messages.frontend_messages.crypt_windows.__encrypt":{
  "__set__":true,
  "elements":[
   "vertica-python-0.6.13-py35_0",
   "vertica-python-0.6.14-py35_0"
  ]
 },
 "vertica_python.vertica.messages.frontend_messages.crypt_windows.__setkey":{
  "__set__":true,
  "elements":[
   "vertica-python-0.6.13-py35_0",
   "vertica-python-0.6.14-py35_0"
  ]
 },
 "vertica_python.vertica.messages.frontend_messages.crypt_windows.crypt":{
  "__set__":true,
  "elements":[
   "vertica-python-0.6.13-py35_0",
   "vertica-python-0.6.14-py35_0"
  ]
 },
 "vertica_python.vertica.messages.frontend_messages.crypt_windows.e2":{
  "__set__":true,
  "elements":[
   "vertica-python-0.6.13-py35_0",
   "vertica-python-0.6.14-py35_0"
  ]
 },
 "vertica_python.vertica.messages.frontend_messages.crypt_windows.preS":{
  "__set__":true,
  "elements":[
   "vertica-python-0.6.13-py35_0",
   "vertica-python-0.6.14-py35_0"
  ]
 },
 "vertica_python.vertica.messages.frontend_messages.describe":{
  "__set__":true,
  "elements":[
   "vertica-python-0.6.13-py35_0",
   "vertica-python-0.6.14-py35_0"
  ]
 },
 "vertica_python.vertica.messages.frontend_messages.describe.Describe":{
  "__set__":true,
  "elements":[
   "vertica-python-0.6.13-py35_0",
   "vertica-python-0.6.14-py35_0"
  ]
 },
 "vertica_python.vertica.messages.frontend_messages.describe.FrontendMessage":{
  "__set__":true,
  "elements":[
   "vertica-python-0.6.13-py35_0",
   "vertica-python-0.6.14-py35_0"
  ]
 },
 "vertica_python.vertica.messages.frontend_messages.execute":{
  "__set__":true,
  "elements":[
   "vertica-python-0.6.13-py35_0",
   "vertica-python-0.6.14-py35_0"
  ]
 },
 "vertica_python.vertica.messages.frontend_messages.execute.Execute":{
  "__set__":true,
  "elements":[
   "vertica-python-0.6.13-py35_0",
   "vertica-python-0.6.14-py35_0"
  ]
 },
 "vertica_python.vertica.messages.frontend_messages.execute.FrontendMessage":{
  "__set__":true,
  "elements":[
   "vertica-python-0.6.13-py35_0",
   "vertica-python-0.6.14-py35_0"
  ]
 },
 "vertica_python.vertica.messages.frontend_messages.flush":{
  "__set__":true,
  "elements":[
   "vertica-python-0.6.13-py35_0",
   "vertica-python-0.6.14-py35_0"
  ]
 },
 "vertica_python.vertica.messages.frontend_messages.flush.Flush":{
  "__set__":true,
  "elements":[
   "vertica-python-0.6.13-py35_0",
   "vertica-python-0.6.14-py35_0"
  ]
 },
 "vertica_python.vertica.messages.frontend_messages.flush.FrontendMessage":{
  "__set__":true,
  "elements":[
   "vertica-python-0.6.13-py35_0",
   "vertica-python-0.6.14-py35_0"
  ]
 },
 "vertica_python.vertica.messages.frontend_messages.parse":{
  "__set__":true,
  "elements":[
   "vertica-python-0.6.13-py35_0",
   "vertica-python-0.6.14-py35_0"
  ]
 },
 "vertica_python.vertica.messages.frontend_messages.parse.FrontendMessage":{
  "__set__":true,
  "elements":[
   "vertica-python-0.6.13-py35_0",
   "vertica-python-0.6.14-py35_0"
  ]
 },
 "vertica_python.vertica.messages.frontend_messages.parse.Parse":{
  "__set__":true,
  "elements":[
   "vertica-python-0.6.13-py35_0",
   "vertica-python-0.6.14-py35_0"
  ]
 },
 "vertica_python.vertica.messages.frontend_messages.password":{
  "__set__":true,
  "elements":[
   "vertica-python-0.6.13-py35_0",
   "vertica-python-0.6.14-py35_0"
  ]
 },
 "vertica_python.vertica.messages.frontend_messages.password.Authentication":{
  "__set__":true,
  "elements":[
   "vertica-python-0.6.13-py35_0",
   "vertica-python-0.6.14-py35_0"
  ]
 },
 "vertica_python.vertica.messages.frontend_messages.password.FrontendMessage":{
  "__set__":true,
  "elements":[
   "vertica-python-0.6.13-py35_0",
   "vertica-python-0.6.14-py35_0"
  ]
 },
 "vertica_python.vertica.messages.frontend_messages.password.Password":{
  "__set__":true,
  "elements":[
   "vertica-python-0.6.13-py35_0",
   "vertica-python-0.6.14-py35_0"
  ]
 },
 "vertica_python.vertica.messages.frontend_messages.query":{
  "__set__":true,
  "elements":[
   "vertica-python-0.6.13-py35_0",
   "vertica-python-0.6.14-py35_0"
  ]
 },
 "vertica_python.vertica.messages.frontend_messages.query.FrontendMessage":{
  "__set__":true,
  "elements":[
   "vertica-python-0.6.13-py35_0",
   "vertica-python-0.6.14-py35_0"
  ]
 },
 "vertica_python.vertica.messages.frontend_messages.query.Query":{
  "__set__":true,
  "elements":[
   "vertica-python-0.6.13-py35_0",
   "vertica-python-0.6.14-py35_0"
  ]
 },
 "vertica_python.vertica.messages.frontend_messages.ssl_request":{
  "__set__":true,
  "elements":[
   "vertica-python-0.6.13-py35_0",
   "vertica-python-0.6.14-py35_0"
  ]
 },
 "vertica_python.vertica.messages.frontend_messages.ssl_request.FrontendMessage":{
  "__set__":true,
  "elements":[
   "vertica-python-0.6.13-py35_0",
   "vertica-python-0.6.14-py35_0"
  ]
 },
 "vertica_python.vertica.messages.frontend_messages.ssl_request.SslRequest":{
  "__set__":true,
  "elements":[
   "vertica-python-0.6.13-py35_0",
   "vertica-python-0.6.14-py35_0"
  ]
 },
 "vertica_python.vertica.messages.frontend_messages.startup":{
  "__set__":true,
  "elements":[
   "vertica-python-0.6.13-py35_0",
   "vertica-python-0.6.14-py35_0"
  ]
 },
 "vertica_python.vertica.messages.frontend_messages.startup.FrontendMessage":{
  "__set__":true,
  "elements":[
   "vertica-python-0.6.13-py35_0",
   "vertica-python-0.6.14-py35_0"
  ]
 },
 "vertica_python.vertica.messages.frontend_messages.startup.Startup":{
  "__set__":true,
  "elements":[
   "vertica-python-0.6.13-py35_0",
   "vertica-python-0.6.14-py35_0"
  ]
 },
 "vertica_python.vertica.messages.frontend_messages.sync":{
  "__set__":true,
  "elements":[
   "vertica-python-0.6.13-py35_0",
   "vertica-python-0.6.14-py35_0"
  ]
 },
 "vertica_python.vertica.messages.frontend_messages.sync.FrontendMessage":{
  "__set__":true,
  "elements":[
   "vertica-python-0.6.13-py35_0",
   "vertica-python-0.6.14-py35_0"
  ]
 },
 "vertica_python.vertica.messages.frontend_messages.sync.Sync":{
  "__set__":true,
  "elements":[
   "vertica-python-0.6.13-py35_0",
   "vertica-python-0.6.14-py35_0"
  ]
 },
 "vertica_python.vertica.messages.frontend_messages.terminate":{
  "__set__":true,
  "elements":[
   "vertica-python-0.6.13-py35_0",
   "vertica-python-0.6.14-py35_0"
  ]
 },
 "vertica_python.vertica.messages.frontend_messages.terminate.FrontendMessage":{
  "__set__":true,
  "elements":[
   "vertica-python-0.6.13-py35_0",
   "vertica-python-0.6.14-py35_0"
  ]
 },
 "vertica_python.vertica.messages.frontend_messages.terminate.Terminate":{
  "__set__":true,
  "elements":[
   "vertica-python-0.6.13-py35_0",
   "vertica-python-0.6.14-py35_0"
  ]
 },
 "vertica_python.vertica.messages.message":{
  "__set__":true,
  "elements":[
   "vertica-python-0.6.13-py35_0",
   "vertica-python-0.6.14-py35_0"
  ]
 },
 "vertica_python.vertica.messages.message.Authentication":{
  "__set__":true,
  "elements":[
   "vertica-python-0.6.13-py35_0",
   "vertica-python-0.6.14-py35_0"
  ]
 },
 "vertica_python.vertica.messages.message.BackendKeyData":{
  "__set__":true,
  "elements":[
   "vertica-python-0.6.13-py35_0",
   "vertica-python-0.6.14-py35_0"
  ]
 },
 "vertica_python.vertica.messages.message.BackendMessage":{
  "__set__":true,
  "elements":[
   "vertica-python-0.6.13-py35_0",
   "vertica-python-0.6.14-py35_0"
  ]
 },
 "vertica_python.vertica.messages.message.Bind":{
  "__set__":true,
  "elements":[
   "vertica-python-0.6.13-py35_0",
   "vertica-python-0.6.14-py35_0"
  ]
 },
 "vertica_python.vertica.messages.message.CancelRequest":{
  "__set__":true,
  "elements":[
   "vertica-python-0.6.13-py35_0",
   "vertica-python-0.6.14-py35_0"
  ]
 },
 "vertica_python.vertica.messages.message.Close":{
  "__set__":true,
  "elements":[
   "vertica-python-0.6.13-py35_0",
   "vertica-python-0.6.14-py35_0"
  ]
 },
 "vertica_python.vertica.messages.message.CommandComplete":{
  "__set__":true,
  "elements":[
   "vertica-python-0.6.13-py35_0",
   "vertica-python-0.6.14-py35_0"
  ]
 },
 "vertica_python.vertica.messages.message.CopyData":{
  "__set__":true,
  "elements":[
   "vertica-python-0.6.13-py35_0",
   "vertica-python-0.6.14-py35_0"
  ]
 },
 "vertica_python.vertica.messages.message.CopyDone":{
  "__set__":true,
  "elements":[
   "vertica-python-0.6.13-py35_0",
   "vertica-python-0.6.14-py35_0"
  ]
 },
 "vertica_python.vertica.messages.message.CopyFail":{
  "__set__":true,
  "elements":[
   "vertica-python-0.6.13-py35_0",
   "vertica-python-0.6.14-py35_0"
  ]
 },
 "vertica_python.vertica.messages.message.CopyInResponse":{
  "__set__":true,
  "elements":[
   "vertica-python-0.6.13-py35_0",
   "vertica-python-0.6.14-py35_0"
  ]
 },
 "vertica_python.vertica.messages.message.CopyStream":{
  "__set__":true,
  "elements":[
   "vertica-python-0.6.13-py35_0",
   "vertica-python-0.6.14-py35_0"
  ]
 },
 "vertica_python.vertica.messages.message.DataRow":{
  "__set__":true,
  "elements":[
   "vertica-python-0.6.13-py35_0",
   "vertica-python-0.6.14-py35_0"
  ]
 },
 "vertica_python.vertica.messages.message.Describe":{
  "__set__":true,
  "elements":[
   "vertica-python-0.6.13-py35_0",
   "vertica-python-0.6.14-py35_0"
  ]
 },
 "vertica_python.vertica.messages.message.EmptyQueryResponse":{
  "__set__":true,
  "elements":[
   "vertica-python-0.6.13-py35_0",
   "vertica-python-0.6.14-py35_0"
  ]
 },
 "vertica_python.vertica.messages.message.ErrorResponse":{
  "__set__":true,
  "elements":[
   "vertica-python-0.6.13-py35_0",
   "vertica-python-0.6.14-py35_0"
  ]
 },
 "vertica_python.vertica.messages.message.Execute":{
  "__set__":true,
  "elements":[
   "vertica-python-0.6.13-py35_0",
   "vertica-python-0.6.14-py35_0"
  ]
 },
 "vertica_python.vertica.messages.message.Flush":{
  "__set__":true,
  "elements":[
   "vertica-python-0.6.13-py35_0",
   "vertica-python-0.6.14-py35_0"
  ]
 },
 "vertica_python.vertica.messages.message.FrontendMessage":{
  "__set__":true,
  "elements":[
   "vertica-python-0.6.13-py35_0",
   "vertica-python-0.6.14-py35_0"
  ]
 },
 "vertica_python.vertica.messages.message.Message":{
  "__set__":true,
  "elements":[
   "vertica-python-0.6.13-py35_0",
   "vertica-python-0.6.14-py35_0"
  ]
 },
 "vertica_python.vertica.messages.message.NoData":{
  "__set__":true,
  "elements":[
   "vertica-python-0.6.13-py35_0",
   "vertica-python-0.6.14-py35_0"
  ]
 },
 "vertica_python.vertica.messages.message.NoticeResponse":{
  "__set__":true,
  "elements":[
   "vertica-python-0.6.13-py35_0",
   "vertica-python-0.6.14-py35_0"
  ]
 },
 "vertica_python.vertica.messages.message.ParameterDescription":{
  "__set__":true,
  "elements":[
   "vertica-python-0.6.13-py35_0",
   "vertica-python-0.6.14-py35_0"
  ]
 },
 "vertica_python.vertica.messages.message.ParameterStatus":{
  "__set__":true,
  "elements":[
   "vertica-python-0.6.13-py35_0",
   "vertica-python-0.6.14-py35_0"
  ]
 },
 "vertica_python.vertica.messages.message.Parse":{
  "__set__":true,
  "elements":[
   "vertica-python-0.6.13-py35_0",
   "vertica-python-0.6.14-py35_0"
  ]
 },
 "vertica_python.vertica.messages.message.Password":{
  "__set__":true,
  "elements":[
   "vertica-python-0.6.13-py35_0",
   "vertica-python-0.6.14-py35_0"
  ]
 },
 "vertica_python.vertica.messages.message.PortalSuspended":{
  "__set__":true,
  "elements":[
   "vertica-python-0.6.13-py35_0",
   "vertica-python-0.6.14-py35_0"
  ]
 },
 "vertica_python.vertica.messages.message.Query":{
  "__set__":true,
  "elements":[
   "vertica-python-0.6.13-py35_0",
   "vertica-python-0.6.14-py35_0"
  ]
 },
 "vertica_python.vertica.messages.message.ReadyForQuery":{
  "__set__":true,
  "elements":[
   "vertica-python-0.6.13-py35_0",
   "vertica-python-0.6.14-py35_0"
  ]
 },
 "vertica_python.vertica.messages.message.RowDescription":{
  "__set__":true,
  "elements":[
   "vertica-python-0.6.13-py35_0",
   "vertica-python-0.6.14-py35_0"
  ]
 },
 "vertica_python.vertica.messages.message.SslRequest":{
  "__set__":true,
  "elements":[
   "vertica-python-0.6.13-py35_0",
   "vertica-python-0.6.14-py35_0"
  ]
 },
 "vertica_python.vertica.messages.message.Startup":{
  "__set__":true,
  "elements":[
   "vertica-python-0.6.13-py35_0",
   "vertica-python-0.6.14-py35_0"
  ]
 },
 "vertica_python.vertica.messages.message.Sync":{
  "__set__":true,
  "elements":[
   "vertica-python-0.6.13-py35_0",
   "vertica-python-0.6.14-py35_0"
  ]
 },
 "vertica_python.vertica.messages.message.Terminate":{
  "__set__":true,
  "elements":[
   "vertica-python-0.6.13-py35_0",
   "vertica-python-0.6.14-py35_0"
  ]
 },
 "vertica_python.vertica.messages.message.Unknown":{
  "__set__":true,
  "elements":[
   "vertica-python-0.6.13-py35_0",
   "vertica-python-0.6.14-py35_0"
  ]
 },
 "vertica_python.vertica.messages.message.__all__":{
  "__set__":true,
  "elements":[
   "vertica-python-0.6.13-py35_0",
   "vertica-python-0.6.14-py35_0"
  ]
 }
}