{
 "errors": {
  "geopandas.array": {
   "exception": "'NoneType' object has no attribute 'type'",
   "traceback": [
    "Traceback (most recent call last):",
    "  File \"/usr/share/miniconda/envs/test/lib/python3.7/site-packages/symbol_exporter/symbol_inspection.py\", line 34, in single_file_extraction",
    "    data = jedi.Script(path=file_name, project=jedi.Project(''.join(top_dir))).complete()",
    "  File \"/usr/share/miniconda/envs/test/lib/python3.7/site-packages/jedi/api/helpers.py\", line 488, in wrapper",
    "    return func(self, line, column, *args, **kwargs)",
    "  File \"/usr/share/miniconda/envs/test/lib/python3.7/site-packages/jedi/api/__init__.py\", line 213, in complete",
    "    return completion.complete()",
    "  File \"/usr/share/miniconda/envs/test/lib/python3.7/site-packages/jedi/api/completion.py\", line 169, in complete",
    "    cached_name, completion_names = self._complete_python(leaf)",
    "  File \"/usr/share/miniconda/envs/test/lib/python3.7/site-packages/jedi/api/completion.py\", line 311, in _complete_python",
    "    completion_names += self._complete_inherited(is_function=False)",
    "  File \"/usr/share/miniconda/envs/test/lib/python3.7/site-packages/jedi/api/completion.py\", line 428, in _complete_inherited",
    "    if (name.api_type == 'function') == is_function:",
    "  File \"/usr/share/miniconda/envs/test/lib/python3.7/site-packages/jedi/inference/value/klass.py\", line 80, in api_type",
    "    if definition.type == 'funcdef':",
    "AttributeError: 'NoneType' object has no attribute 'type'",
    ""
   ]
  },
  "geopandas.geoseries": {
   "exception": "'NoneType' object has no attribute 'type'",
   "traceback": [
    "Traceback (most recent call last):",
    "  File \"/usr/share/miniconda/envs/test/lib/python3.7/site-packages/symbol_exporter/symbol_inspection.py\", line 34, in single_file_extraction",
    "    data = jedi.Script(path=file_name, project=jedi.Project(''.join(top_dir))).complete()",
    "  File \"/usr/share/miniconda/envs/test/lib/python3.7/site-packages/jedi/api/helpers.py\", line 488, in wrapper",
    "    return func(self, line, column, *args, **kwargs)",
    "  File \"/usr/share/miniconda/envs/test/lib/python3.7/site-packages/jedi/api/__init__.py\", line 213, in complete",
    "    return completion.complete()",
    "  File \"/usr/share/miniconda/envs/test/lib/python3.7/site-packages/jedi/api/completion.py\", line 169, in complete",
    "    cached_name, completion_names = self._complete_python(leaf)",
    "  File \"/usr/share/miniconda/envs/test/lib/python3.7/site-packages/jedi/api/completion.py\", line 311, in _complete_python",
    "    completion_names += self._complete_inherited(is_function=False)",
    "  File \"/usr/share/miniconda/envs/test/lib/python3.7/site-packages/jedi/api/completion.py\", line 428, in _complete_inherited",
    "    if (name.api_type == 'function') == is_function:",
    "  File \"/usr/share/miniconda/envs/test/lib/python3.7/site-packages/jedi/inference/value/klass.py\", line 80, in api_type",
    "    if definition.type == 'funcdef':",
    "AttributeError: 'NoneType' object has no attribute 'type'",
    ""
   ]
  }
 },
 "symbols": [
  "geopandas.GeoDataFrame",
  "geopandas.GeoSeries",
  "geopandas.__version__",
  "geopandas._compat",
  "geopandas._compat.PANDAS_GE_024",
  "geopandas._compat.PANDAS_GE_025",
  "geopandas._compat.PANDAS_GE_10",
  "geopandas._config",
  "geopandas._config.Option",
  "geopandas._config.Options",
  "geopandas._config._validate_display_precision",
  "geopandas._config.display_precision",
  "geopandas._config.indent",
  "geopandas._config.options",
  "geopandas._points_from_xy",
  "geopandas._version",
  "geopandas._version.get_versions",
  "geopandas._version.version_json",
  "geopandas.array",
  "geopandas.array.GeometryArray",
  "geopandas.array.GeometryDtype",
  "geopandas.array._points_from_xy",
  "geopandas.array.from_shapely",
  "geopandas.array.from_wkb",
  "geopandas.array.from_wkt",
  "geopandas.array.points_from_xy",
  "geopandas.array.to_wkb",
  "geopandas.array.to_wkt",
  "geopandas.base",
  "geopandas.base.GeoPandasBase",
  "geopandas.base.HAS_SINDEX",
  "geopandas.base.RTreeError",
  "geopandas.base._CoordinateIndexer",
  "geopandas.base._binary_geo",
  "geopandas.base._binary_op",
  "geopandas.base._delegate_binary_method",
  "geopandas.base._delegate_geo_method",
  "geopandas.base._delegate_property",
  "geopandas.base.is_geometry_type",
  "geopandas.clip",
  "geopandas.datasets",
  "geopandas.datasets.__all__",
  "geopandas.datasets._available_dir",
  "geopandas.datasets._available_zip",
  "geopandas.datasets._module_path",
  "geopandas.datasets.available",
  "geopandas.datasets.get_path",
  "geopandas.datasets.naturalearth_creation",
  "geopandas.datasets.naturalearth_creation.world_df",
  "geopandas.datasets.naturalearth_creation.world_raw",
  "geopandas.geodataframe",
  "geopandas.geodataframe.DEFAULT_GEO_COLUMN_NAME",
  "geopandas.geodataframe.GeoDataFrame",
  "geopandas.geodataframe.GeoPandasBase",
  "geopandas.geodataframe.GeoSeries",
  "geopandas.geodataframe.GeometryArray",
  "geopandas.geodataframe._dataframe_set_geometry",
  "geopandas.geodataframe._ensure_geometry",
  "geopandas.geodataframe.from_shapely",
  "geopandas.geodataframe.is_geometry_type",
  "geopandas.geodataframe.plot_dataframe",
  "geopandas.geoseries",
  "geopandas.geoseries.GeoSeries",
  "geopandas.io",
  "geopandas.io.file",
  "geopandas.io.file.GeoDataFrame",
  "geopandas.io.file.GeoSeries",
  "geopandas.io.file._FIONA18",
  "geopandas.io.file._VALID_URLS",
  "geopandas.io.file._geometry_types",
  "geopandas.io.file._is_url",
  "geopandas.io.file.infer_schema",
  "geopandas.io.file.read_file",
  "geopandas.io.file.to_file",
  "geopandas.io.sql",
  "geopandas.io.sql.GeoDataFrame",
  "geopandas.io.sql.read_postgis",
  "geopandas.options",
  "geopandas.overlay",
  "geopandas.plotting",
  "geopandas.plotting._flatten_multi_geoms",
  "geopandas.plotting._mapclassify_choro",
  "geopandas.plotting.plot_dataframe",
  "geopandas.plotting.plot_linestring_collection",
  "geopandas.plotting.plot_point_collection",
  "geopandas.plotting.plot_polygon_collection",
  "geopandas.plotting.plot_series",
  "geopandas.points_from_xy",
  "geopandas.read_file",
  "geopandas.read_postgis",
  "geopandas.show_versions",
  "geopandas.sindex",
  "geopandas.sindex.SpatialIndex",
  "geopandas.sindex.base",
  "geopandas.sjoin",
  "geopandas.testing",
  "geopandas.testing.GeoDataFrame",
  "geopandas.testing.GeoSeries",
  "geopandas.testing.GeometryDtype",
  "geopandas.testing._isna",
  "geopandas.testing.assert_geodataframe_equal",
  "geopandas.testing.assert_geoseries_equal",
  "geopandas.testing.geom_almost_equals",
  "geopandas.testing.geom_equals",
  "geopandas.tests",
  "geopandas.tests.test_api",
  "geopandas.tests.test_api.PANDAS_GE_10",
  "geopandas.tests.test_api.test_no_additional_imports",
  "geopandas.tests.test_array",
  "geopandas.tests.test_array.GeometryArray",
  "geopandas.tests.test_array.P",
  "geopandas.tests.test_array.T",
  "geopandas.tests.test_array.equal_geometries",
  "geopandas.tests.test_array.from_shapely",
  "geopandas.tests.test_array.from_wkb",
  "geopandas.tests.test_array.from_wkt",
  "geopandas.tests.test_array.points",
  "geopandas.tests.test_array.points_from_xy",
  "geopandas.tests.test_array.points_no_missing",
  "geopandas.tests.test_array.test_affinity_methods",
  "geopandas.tests.test_array.test_astype_multipolygon",
  "geopandas.tests.test_array.test_binary_distance",
  "geopandas.tests.test_array.test_binary_geo_scalar",
  "geopandas.tests.test_array.test_binary_geo_vector",
  "geopandas.tests.test_array.test_binary_project",
  "geopandas.tests.test_array.test_binary_relate",
  "geopandas.tests.test_array.test_bounds",
  "geopandas.tests.test_array.test_buffer",
  "geopandas.tests.test_array.test_chaining",
  "geopandas.tests.test_array.test_coords_x_y",
  "geopandas.tests.test_array.test_dir",
  "geopandas.tests.test_array.test_equality_ops",
  "geopandas.tests.test_array.test_from_shapely",
  "geopandas.tests.test_array.test_from_wkb",
  "geopandas.tests.test_array.test_from_wkt",
  "geopandas.tests.test_array.test_geom_types",
  "geopandas.tests.test_array.test_getitem",
  "geopandas.tests.test_array.test_pickle",
  "geopandas.tests.test_array.test_points",
  "geopandas.tests.test_array.test_predicates_vector_scalar",
  "geopandas.tests.test_array.test_predicates_vector_vector",
  "geopandas.tests.test_array.test_raise_on_bad_sizes",
  "geopandas.tests.test_array.test_simplify",
  "geopandas.tests.test_array.test_to_wkb",
  "geopandas.tests.test_array.test_to_wkt",
  "geopandas.tests.test_array.test_total_bounds",
  "geopandas.tests.test_array.test_unary_float",
  "geopandas.tests.test_array.test_unary_geo",
  "geopandas.tests.test_array.test_unary_predicates",
  "geopandas.tests.test_array.test_unary_union",
  "geopandas.tests.test_array.to_wkb",
  "geopandas.tests.test_array.to_wkt",
  "geopandas.tests.test_array.triangle_no_missing",
  "geopandas.tests.test_array.triangles",
  "geopandas.tests.test_config",
  "geopandas.tests.test_config.test_options",
  "geopandas.tests.test_crs",
  "geopandas.tests.test_crs.GeoDataFrame",
  "geopandas.tests.test_crs.PYPROJ_LT_231",
  "geopandas.tests.test_crs._create_df",
  "geopandas.tests.test_crs.assert_geodataframe_equal",
  "geopandas.tests.test_crs.df_epsg26918",
  "geopandas.tests.test_crs.epsg26918",
  "geopandas.tests.test_crs.epsg4326",
  "geopandas.tests.test_crs.points_from_xy",
  "geopandas.tests.test_crs.test_crs_axis_order__always_xy",
  "geopandas.tests.test_crs.test_skip_exact_same",
  "geopandas.tests.test_crs.test_to_crs_geo_column_name",
  "geopandas.tests.test_crs.test_to_crs_inplace",
  "geopandas.tests.test_crs.test_to_crs_transform",
  "geopandas.tests.test_crs.test_transform2",
  "geopandas.tests.test_datasets",
  "geopandas.tests.test_datasets.GeoDataFrame",
  "geopandas.tests.test_datasets.get_path",
  "geopandas.tests.test_datasets.read_file",
  "geopandas.tests.test_datasets.test_read_paths",
  "geopandas.tests.test_dissolve",
  "geopandas.tests.test_dissolve.GeoDataFrame",
  "geopandas.tests.test_dissolve.expected_mean",
  "geopandas.tests.test_dissolve.first_dissolve",
  "geopandas.tests.test_dissolve.merged_shapes",
  "geopandas.tests.test_dissolve.read_file",
  "geopandas.tests.test_dissolve.test_dissolve_retains_existing_crs",
  "geopandas.tests.test_dissolve.test_dissolve_retains_nonexisting_crs",
  "geopandas.tests.test_dissolve.test_geom_dissolve",
  "geopandas.tests.test_dissolve.test_mean_dissolve",
  "geopandas.tests.test_dissolve.test_multicolumn_dissolve",
  "geopandas.tests.test_dissolve.test_reset_index",
  "geopandas.tests.test_extension_array",
  "geopandas.tests.test_extension_array.GeometryArray",
  "geopandas.tests.test_extension_array.GeometryDtype",
  "geopandas.tests.test_extension_array.PANDAS_GE_024",
  "geopandas.tests.test_extension_array.TestArithmeticOps",
  "geopandas.tests.test_extension_array.TestCasting",
  "geopandas.tests.test_extension_array.TestComparisonOps",
  "geopandas.tests.test_extension_array.TestConstructors",
  "geopandas.tests.test_extension_array.TestDtype",
  "geopandas.tests.test_extension_array.TestGetitem",
  "geopandas.tests.test_extension_array.TestGroupby",
  "geopandas.tests.test_extension_array.TestInterface",
  "geopandas.tests.test_extension_array.TestMethods",
  "geopandas.tests.test_extension_array.TestMissing",
  "geopandas.tests.test_extension_array.TestParsing",
  "geopandas.tests.test_extension_array.TestPrinting",
  "geopandas.tests.test_extension_array.TestReduce",
  "geopandas.tests.test_extension_array.TestReshaping",
  "geopandas.tests.test_extension_array.TestSetitem",
  "geopandas.tests.test_extension_array._all_arithmetic_operators",
  "geopandas.tests.test_extension_array.all_arithmetic_operators",
  "geopandas.tests.test_extension_array.all_boolean_reductions",
  "geopandas.tests.test_extension_array.all_compare_operators",
  "geopandas.tests.test_extension_array.all_data",
  "geopandas.tests.test_extension_array.all_numeric_reductions",
  "geopandas.tests.test_extension_array.as_array",
  "geopandas.tests.test_extension_array.as_frame",
  "geopandas.tests.test_extension_array.as_series",
  "geopandas.tests.test_extension_array.box_in_series",
  "geopandas.tests.test_extension_array.data",
  "geopandas.tests.test_extension_array.dtype",
  "geopandas.tests.test_extension_array.fillna_method",
  "geopandas.tests.test_extension_array.from_shapely",
  "geopandas.tests.test_extension_array.groupby_apply_op",
  "geopandas.tests.test_extension_array.make_data",
  "geopandas.tests.test_extension_array.na_cmp",
  "geopandas.tests.test_extension_array.na_value",
  "geopandas.tests.test_extension_array.no_sorting",
  "geopandas.tests.test_extension_array.not_yet_implemented",
  "geopandas.tests.test_extension_array.skip_pandas_below_024",
  "geopandas.tests.test_extension_array.use_numpy",
  "geopandas.tests.test_geocode",
  "geopandas.tests.test_geocode.ForwardMock",
  "geopandas.tests.test_geocode.GeoDataFrame",
  "geopandas.tests.test_geocode.GeoSeries",
  "geopandas.tests.test_geocode.ReverseMock",
  "geopandas.tests.test_geocode._prepare_geocode_result",
  "geopandas.tests.test_geocode.assert_geoseries_equal",
  "geopandas.tests.test_geocode.geocode",
  "geopandas.tests.test_geocode.geopy",
  "geopandas.tests.test_geocode.mock",
  "geopandas.tests.test_geocode.reverse_geocode",
  "geopandas.tests.test_geocode.test_bad_provider_forward",
  "geopandas.tests.test_geocode.test_bad_provider_reverse",
  "geopandas.tests.test_geocode.test_forward",
  "geopandas.tests.test_geocode.test_prepare_result",
  "geopandas.tests.test_geocode.test_reverse",
  "geopandas.tests.test_geodataframe",
  "geopandas.tests.test_geodataframe.GeoDataFrame",
  "geopandas.tests.test_geodataframe.GeoSeries",
  "geopandas.tests.test_geodataframe.GeometryArray",
  "geopandas.tests.test_geodataframe.GeometryDtype",
  "geopandas.tests.test_geodataframe.PACKAGE_DIR",
  "geopandas.tests.test_geodataframe.TestConstructor",
  "geopandas.tests.test_geodataframe.TestDataFrame",
  "geopandas.tests.test_geodataframe.assert_geodataframe_equal",
  "geopandas.tests.test_geodataframe.assert_geoseries_equal",
  "geopandas.tests.test_geodataframe.check_geodataframe",
  "geopandas.tests.test_geodataframe.connect",
  "geopandas.tests.test_geodataframe.create_postgis",
  "geopandas.tests.test_geodataframe.read_file",
  "geopandas.tests.test_geodataframe.test_geodataframe_crs",
  "geopandas.tests.test_geodataframe.validate_boro_df",
  "geopandas.tests.test_geom_methods",
  "geopandas.tests.test_geom_methods.GeoDataFrame",
  "geopandas.tests.test_geom_methods.GeoPandasBase",
  "geopandas.tests.test_geom_methods.GeoSeries",
  "geopandas.tests.test_geom_methods.TestGeomMethods",
  "geopandas.tests.test_geom_methods.assert_array_dtype_equal",
  "geopandas.tests.test_geom_methods.assert_geoseries_equal",
  "geopandas.tests.test_geom_methods.geom_almost_equals",
  "geopandas.tests.test_geom_methods.geom_equals",
  "geopandas.tests.test_geoseries",
  "geopandas.tests.test_geoseries.GeoDataFrame",
  "geopandas.tests.test_geoseries.GeoSeries",
  "geopandas.tests.test_geoseries.GeometryArray",
  "geopandas.tests.test_geoseries.GeometryDtype",
  "geopandas.tests.test_geoseries.TestConstructor",
  "geopandas.tests.test_geoseries.TestSeries",
  "geopandas.tests.test_geoseries.check_geoseries",
  "geopandas.tests.test_geoseries.geom_equals",
  "geopandas.tests.test_geoseries.test_geoseries_crs",
  "geopandas.tests.test_geoseries.test_missing_values",
  "geopandas.tests.test_merge",
  "geopandas.tests.test_merge.GeoDataFrame",
  "geopandas.tests.test_merge.GeoSeries",
  "geopandas.tests.test_merge.TestMerging",
  "geopandas.tests.test_overlay",
  "geopandas.tests.test_overlay.DATA",
  "geopandas.tests.test_overlay.GeoDataFrame",
  "geopandas.tests.test_overlay.GeoSeries",
  "geopandas.tests.test_overlay.assert_geodataframe_equal",
  "geopandas.tests.test_overlay.assert_geoseries_equal",
  "geopandas.tests.test_overlay.dfs",
  "geopandas.tests.test_overlay.how",
  "geopandas.tests.test_overlay.keep_geom_type",
  "geopandas.tests.test_overlay.overlay",
  "geopandas.tests.test_overlay.read_file",
  "geopandas.tests.test_overlay.test_bad_how",
  "geopandas.tests.test_overlay.test_correct_index",
  "geopandas.tests.test_overlay.test_duplicate_column_name",
  "geopandas.tests.test_overlay.test_empty_intersection",
  "geopandas.tests.test_overlay.test_geometry_not_named_geometry",
  "geopandas.tests.test_overlay.test_geoseries_warning",
  "geopandas.tests.test_overlay.test_keep_geom_type_error",
  "geopandas.tests.test_overlay.test_mixed_geom_error",
  "geopandas.tests.test_overlay.test_overlay",
  "geopandas.tests.test_overlay.test_preserve_crs",
  "geopandas.tests.test_pandas_methods",
  "geopandas.tests.test_pandas_methods.GeoDataFrame",
  "geopandas.tests.test_pandas_methods.GeoSeries",
  "geopandas.tests.test_pandas_methods.PANDAS_GE_024",
  "geopandas.tests.test_pandas_methods.PANDAS_GE_025",
  "geopandas.tests.test_pandas_methods.assert_geodataframe_equal",
  "geopandas.tests.test_pandas_methods.assert_geoseries_equal",
  "geopandas.tests.test_pandas_methods.from_shapely",
  "geopandas.tests.test_pandas_methods.s",
  "geopandas.tests.test_pandas_methods.test_any_all",
  "geopandas.tests.test_pandas_methods.test_apply_loc_len1",
  "geopandas.tests.test_pandas_methods.test_assign",
  "geopandas.tests.test_pandas_methods.test_astype",
  "geopandas.tests.test_pandas_methods.test_drop_duplicates_frame",
  "geopandas.tests.test_pandas_methods.test_drop_duplicates_series",
  "geopandas.tests.test_pandas_methods.test_dropna",
  "geopandas.tests.test_pandas_methods.test_fillna",
  "geopandas.tests.test_pandas_methods.test_groupby",
  "geopandas.tests.test_pandas_methods.test_indexing",
  "geopandas.tests.test_pandas_methods.test_isna",
  "geopandas.tests.test_pandas_methods.test_numerical_operations",
  "geopandas.tests.test_pandas_methods.test_reindex",
  "geopandas.tests.test_pandas_methods.test_repr",
  "geopandas.tests.test_pandas_methods.test_select_dtypes",
  "geopandas.tests.test_pandas_methods.test_take",
  "geopandas.tests.test_pandas_methods.test_to_csv",
  "geopandas.tests.test_pandas_methods.test_unique",
  "geopandas.tests.test_pandas_methods.test_value_counts",
  "geopandas.tests.test_pandas_methods.test_where",
  "geopandas.tests.test_plotting",
  "geopandas.tests.test_plotting.GeoDataFrame",
  "geopandas.tests.test_plotting.GeoSeries",
  "geopandas.tests.test_plotting.MPL_DFT_COLOR",
  "geopandas.tests.test_plotting.TestGeometryCollectionPlotting",
  "geopandas.tests.test_plotting.TestLineStringPlotting",
  "geopandas.tests.test_plotting.TestMapclassifyPlotting",
  "geopandas.tests.test_plotting.TestNonuniformGeometryPlotting",
  "geopandas.tests.test_plotting.TestPlotCollections",
  "geopandas.tests.test_plotting.TestPointPlotting",
  "geopandas.tests.test_plotting.TestPointZPlotting",
  "geopandas.tests.test_plotting.TestPolygonPlotting",
  "geopandas.tests.test_plotting.TestPolygonZPlotting",
  "geopandas.tests.test_plotting._check_colors",
  "geopandas.tests.test_plotting._style_to_linestring_onoffseq",
  "geopandas.tests.test_plotting.close_figures",
  "geopandas.tests.test_plotting.cycle",
  "geopandas.tests.test_plotting.get_path",
  "geopandas.tests.test_plotting.matplotlib",
  "geopandas.tests.test_plotting.read_file",
  "geopandas.tests.test_plotting.test_column_values",
  "geopandas.tests.test_show_versions",
  "geopandas.tests.test_show_versions._get_C_info",
  "geopandas.tests.test_show_versions._get_deps_info",
  "geopandas.tests.test_show_versions._get_sys_info",
  "geopandas.tests.test_show_versions.show_versions",
  "geopandas.tests.test_show_versions.test_get_c_info",
  "geopandas.tests.test_show_versions.test_get_deps_info",
  "geopandas.tests.test_show_versions.test_get_sys_info",
  "geopandas.tests.test_show_versions.test_show_versions",
  "geopandas.tests.test_sindex",
  "geopandas.tests.test_sindex.GeoDataFrame",
  "geopandas.tests.test_sindex.GeoSeries",
  "geopandas.tests.test_sindex.TestFrameSindex",
  "geopandas.tests.test_sindex.TestJoinSindex",
  "geopandas.tests.test_sindex.TestSeriesSindex",
  "geopandas.tests.test_sindex.base",
  "geopandas.tests.test_sindex.read_file",
  "geopandas.tests.test_testing",
  "geopandas.tests.test_testing.GeoDataFrame",
  "geopandas.tests.test_testing.GeoSeries",
  "geopandas.tests.test_testing.assert_geodataframe_equal",
  "geopandas.tests.test_testing.assert_geoseries_equal",
  "geopandas.tests.test_testing.s1",
  "geopandas.tests.test_testing.s2",
  "geopandas.tests.test_testing.test_equal_nans",
  "geopandas.tests.test_testing.test_geodataframe",
  "geopandas.tests.test_testing.test_geoseries",
  "geopandas.tests.test_testing.test_ignore_crs_mismatch",
  "geopandas.tests.test_testing.test_no_crs",
  "geopandas.tests.test_types",
  "geopandas.tests.test_types.GeoDataFrame",
  "geopandas.tests.test_types.GeoSeries",
  "geopandas.tests.test_types.TestDataFrame",
  "geopandas.tests.test_types.TestSeries",
  "geopandas.tests.util",
  "geopandas.tests.util.GeoDataFrame",
  "geopandas.tests.util.HERE",
  "geopandas.tests.util.OperationalError",
  "geopandas.tests.util.PACKAGE_DIR",
  "geopandas.tests.util.assert_geoseries_equal",
  "geopandas.tests.util.connect",
  "geopandas.tests.util.create_postgis",
  "geopandas.tests.util.create_spatialite",
  "geopandas.tests.util.geom_almost_equals",
  "geopandas.tests.util.geom_equals",
  "geopandas.tests.util.get_srid",
  "geopandas.tests.util.mock",
  "geopandas.tests.util.validate_boro_df",
  "geopandas.tools",
  "geopandas.tools.__all__",
  "geopandas.tools._show_versions",
  "geopandas.tools._show_versions._get_C_info",
  "geopandas.tools._show_versions._get_deps_info",
  "geopandas.tools._show_versions._get_sys_info",
  "geopandas.tools._show_versions.show_versions",
  "geopandas.tools.clip",
  "geopandas.tools.clip.GeoDataFrame",
  "geopandas.tools.clip.GeoSeries",
  "geopandas.tools.clip._clip_line_poly",
  "geopandas.tools.clip._clip_points",
  "geopandas.tools.clip.clip",
  "geopandas.tools.collect",
  "geopandas.tools.crs",
  "geopandas.tools.crs.epsg_from_crs",
  "geopandas.tools.crs.explicit_crs_from_epsg",
  "geopandas.tools.crs.get_epsg_file_contents",
  "geopandas.tools.explicit_crs_from_epsg",
  "geopandas.tools.geocode",
  "geopandas.tools.geocoding",
  "geopandas.tools.geocoding._get_throttle_time",
  "geopandas.tools.geocoding._prepare_geocode_result",
  "geopandas.tools.geocoding._query",
  "geopandas.tools.geocoding.geocode",
  "geopandas.tools.geocoding.reverse_geocode",
  "geopandas.tools.overlay",
  "geopandas.tools.overlay.GeoDataFrame",
  "geopandas.tools.overlay.GeoSeries",
  "geopandas.tools.overlay._ensure_geometry_column",
  "geopandas.tools.overlay._overlay_difference",
  "geopandas.tools.overlay._overlay_intersection",
  "geopandas.tools.overlay._overlay_symmetric_diff",
  "geopandas.tools.overlay._overlay_union",
  "geopandas.tools.overlay.overlay",
  "geopandas.tools.reverse_geocode",
  "geopandas.tools.sjoin",
  "geopandas.tools.sjoin.GeoDataFrame",
  "geopandas.tools.sjoin.sjoin",
  "geopandas.tools.tests",
  "geopandas.tools.tests.test_clip",
  "geopandas.tools.tests.test_clip.GeoDataFrame",
  "geopandas.tools.tests.test_clip.GeoSeries",
  "geopandas.tools.tests.test_clip.assert_geodataframe_equal",
  "geopandas.tools.tests.test_clip.buffered_locations",
  "geopandas.tools.tests.test_clip.clip",
  "geopandas.tools.tests.test_clip.donut_geometry",
  "geopandas.tools.tests.test_clip.larger_single_rectangle_gdf",
  "geopandas.tools.tests.test_clip.mixed_gdf",
  "geopandas.tools.tests.test_clip.multi_line",
  "geopandas.tools.tests.test_clip.multi_point",
  "geopandas.tools.tests.test_clip.multi_poly_gdf",
  "geopandas.tools.tests.test_clip.point_gdf",
  "geopandas.tools.tests.test_clip.sliver_line",
  "geopandas.tools.tests.test_clip.test_clip_line_keep_slivers",
  "geopandas.tools.tests.test_clip.test_clip_lines",
  "geopandas.tools.tests.test_clip.test_clip_multiline",
  "geopandas.tools.tests.test_clip.test_clip_multipoint",
  "geopandas.tools.tests.test_clip.test_clip_multipoly_keep_geom_type",
  "geopandas.tools.tests.test_clip.test_clip_multipoly_keep_slivers",
  "geopandas.tools.tests.test_clip.test_clip_points",
  "geopandas.tools.tests.test_clip.test_clip_poly",
  "geopandas.tools.tests.test_clip.test_clip_single_multipoly_no_extra_geoms",
  "geopandas.tools.tests.test_clip.test_clip_warning_no_extra_geoms",
  "geopandas.tools.tests.test_clip.test_clip_with_line_extra_geom",
  "geopandas.tools.tests.test_clip.test_clip_with_multipolygon",
  "geopandas.tools.tests.test_clip.test_clip_with_polygon",
  "geopandas.tools.tests.test_clip.test_mixed_geom",
  "geopandas.tools.tests.test_clip.test_mixed_series",
  "geopandas.tools.tests.test_clip.test_non_overlapping_geoms",
  "geopandas.tools.tests.test_clip.test_not_gdf",
  "geopandas.tools.tests.test_clip.test_returns_gdf",
  "geopandas.tools.tests.test_clip.test_returns_series",
  "geopandas.tools.tests.test_clip.test_warning_extra_geoms_mixed",
  "geopandas.tools.tests.test_clip.test_warning_geomcoll",
  "geopandas.tools.tests.test_clip.two_line_gdf",
  "geopandas.tools.tests.test_sjoin",
  "geopandas.tools.tests.test_sjoin.GeoDataFrame",
  "geopandas.tools.tests.test_sjoin.GeoSeries",
  "geopandas.tools.tests.test_sjoin.TestSpatialJoin",
  "geopandas.tools.tests.test_sjoin.base",
  "geopandas.tools.tests.test_sjoin.dfs",
  "geopandas.tools.tests.test_sjoin.read_file",
  "geopandas.tools.tests.test_sjoin.sjoin",
  "geopandas.tools.tests.test_tools",
  "geopandas.tools.tests.test_tools.GeoSeries",
  "geopandas.tools.tests.test_tools.PYPROJ_LT_231",
  "geopandas.tools.tests.test_tools.TestTools",
  "geopandas.tools.tests.test_tools.collect",
  "geopandas.tools.tests.test_tools.epsg_from_crs",
  "geopandas.tools.tests.test_tools.explicit_crs_from_epsg",
  "geopandas.tools.util",
  "geopandas.tools.util._multi_type_map",
  "geopandas.tools.util.collect"
 ]
}